Workbook

Sheet DIODE
A2: DIODE STORE STOCK
A4: RAWMATERIAL CODE | B4: CATAGARE NO | C4: SLNO | D4: PART NO | E4: DESCRIPTION | F4: PHY QTY | G4: RECEIPT | H4: ISSUE | I4: BALANCE | J4: UNIT PRICE | K4: AMOUNT
A5: VN0089DE05001 | B5: DE05001 | C5: 1 | D5: MB10S ( MD7S) | E5: BRIDGE DIODE | F5: 0 | G5: 0 | H5: 0 | I5: 3000 | J5: 4.5 | K5: =I5*J5 -> 13500
A6: SM0105DE05002 | B6: DE05002 | C6: 2 | D6: SMUA2121 207 1P | E6: BRIDGE DIODE | I6: =F6+G6-H6 -> 0 | J6: 3.5 | K6: =I6*J6 -> 0
A7: SM0105DE05003 | B7: DE05003 | C7: 3 | D7: MSU2N60 | E7: BRIDGE DIODE | I7: =F7+G7-H7 -> 0 | J7: 5.52 | K7: =I7*J7 -> 0
A8: VN0064DE05004 | B8: DE05004 | C8: 4 | D8: SIM BRIDGE DIODE | E8: BRIDGE DIODE | I8: =F8+G8-H8 -> 0 | J8: 5.9 | K8: =I8*J8 -> 0
A9: SM0105DE05005 | B9: DE05005 | C9: 5 | D9: S2G | E9: BRIDGE DIODE | I9: =F9+G9-H9 -> 0 | J9: 0 | K9: =I9*J9 -> 0
A10: VN0089DE05006 | B10: DE05006 | C10: 6 | D10: SM4007 MELF | E10: BRIDGE DIODE | F10: 250 | I10: =F10+G10-H10 -> 250 | J10: 0.65 | K10: =I10*J10 -> 162.5
A11: VN0101DE05007 | B11: DE05007 | C11: 7 | D11: SR3100 | E11: DIODE | F11: 137 | I11: =F11+G11-H11 -> 137 | J11: 2.9 | K11: =I11*J11 -> 397.3
A12: VN0101DE05008 | B12: DE05008 | C12: 8 | D12: IN4007 | E12: DIODE | F12: 820 | G12: 60000 | H12: =10+10 -> 20 | I12: =F12+G12-H12 -> 60800 | J12: 1 | K12: =I12*J12 -> 60800
A13: VN0064DE05009 | B13: DE05009 | C13: 9 | D13: PK IN 5333B | E13: DIODE | I13: =F13+G13-H13 -> 0 | J13: 2.9 | K13: =I13*J13 -> 0
A14: VN0064DE05010 | B14: DE05010 | C14: 10 | D14: SR260 | E14: DIODE | I14: =F14+G14-H14 -> 0 | J14: 2.9 | K14: =I14*J14 -> 0
A15: VN0064DE05011 | B15: DE05011 | C15: 11 | D15: ES2G /MURS360 | E15: DIODE | G15: =400+750+1500 -> 2650 | H15: =400+200+550 -> 1150 | I15: =F15+G15-H15 -> 1500 | J15: 3.5 | K15: =I15*J15 -> 5250
A16: VN0101DE05012 | B16: DE05012 | C16: 12 | D16: SMD DIODE 39V/S0D-80 | E16: ZENER DIODE | F16: 30 | I16: =F16+G16-H16 -> 30 | J16: 1.47 | K16: =I16*J16 -> 44.1
A17: VN0082DE05013 | B17: DE05013 | C17: 13 | D17: MUR460 | E17: DIODE | F17: =603+4+250+3000+95+603 -> 4555 | G17: 4800 | H17: =10+702+1000+5 -> 1717 | I17: 11138 | J17: 3.5 | K17: =I17*J17 -> 38983
A18: VN0082DE05014 | B18: DE05014 | C18: 14 | D18: 10K TRIM POT | E18: TRIM POT | G18: 5000 | I18: =F18+G18-H18 -> 5000 | J18: 1.65 | K18: =I18*J18 -> 8250
A19: VN0089DE05015 | B19: DE05015 | C19: 15 | D19: SMD DIODE 1N4148 SOD-123 | E19: DIODE | G19: 2000 | H19: 2000 | I19: =F19+G19-H19 -> 0 | J19: 1.1 | K19: =I19*J19 -> 0
A20: VN0089DE05016 | B20: DE05016 | C20: 16 | D20: US1K | E20: DIODE | I20: =F20+G20-H20 -> 0 | J20: 4.9 | K20: =I20*J20 -> 0
A21: VN0009DE05017 | B21: DE05017 | C21: 17 | D21: MUR260/HER206 | E21: DIODE | F21: 500 | I21: =F21+G21-H21 -> 500 | J21: 3 | K21: =I21*J21 -> 1500
B22: DE05018 | C22: 18 | D22: 1N5819 | E22: DIODE | I22: =F22+G22-H22 -> 0 | K22: =I22*J22 -> 0
B23: DE05019 | D23: SMD DIODE USIM | E23: DIODE | I23: =F23+G23-H23 -> 0 | K23: =I23*J23 -> 0
B24: DE05020 | D24: SMD DIODE 1N4007 (m7) | E24: SMD DIODE | G24: =10000+10000 -> 20000 | I24: =F24+G24-H24 -> 20000 | J24: 0.45 | K24: =I24*J24 -> 9000
B25: DE05021 | D25: SMD DIODE UF4003 | E25: SMD DIODE | I25: =F25+G25-H25 -> 0 | K25: =I25*J25 -> 0
B26: DE05022 | D26: DIODE UF 4007 | E26: DIODE | F26: 0 | G26: 30000 | I26: =F26+G26-H26 -> 30000 | J26: 0.65 | K26: =I26*J26 -> 19500
I27: =F27+G27-H27 -> 0 | J27: TOTAL | K27: =SUM(K5:K26) -> 157386.9

Sheet LEDS
A3: LED"S STORE STOCK
A5: RAWMATERIAL CODE | B5: CATAGARE NO | C5: SLNO | D5: PART NO | E5: DESCRIPTION | F5: PHY QTY | G5: RECEIPT | H5: ISSUE | I5: BALANCE | J5: UNIT PRICE | K5: AMOUNT
A6: SMLW56LD00001 | B6: LD00001 | C6: 1 | D6: SMLW56RGB,1W | E6: LED | F6: 956 | I6: =F6+G6-H6 -> 956 | J6: 30 | K6: =I6*J6 -> 28680
A7: VN0094LD00002 | B7: LD00002 | C7: 2 | D7: EW3528D-0201-XBXC-0558 | E7: LED | F7: 910 | I7: 200 | J7: 1.2 | K7: =I7*J7 -> 240
A8: VN0110LD00003 | B8: LD00003 | C8: 3 | D8: WU2180-07 ,3WATT LED | E8: LED | F8: 0 | I8: =F8+G8-H8 -> 0 | J8: 30 | K8: =I8*J8 -> 0
A9: VN0094LD00004 | B9: LD00004 | C9: 4 | D9: FM-5630WLS-460W-R80(WW) | E9: LED | F9: 7449 | I9: 9547 | J9: 6.5 | K9: =I9*J9 -> 62055.5
A10: VN0094LD00005 | B10: LD00005 | C10: 5 | D10: FM-5630WNS-460W-R80 (MW) | E10: LED | F10: 7400 | H10: =1500+1400+5 -> 2905 | I10: 5159 | J10: 6 | K10: =I10*J10 -> 30954
A11: VN0094LD00006 | B11: LD00006 | C11: 6 | D11: FM-3528WNS-460R ( NT10TN1S23B) | E11: LED | F11: 275 | H11: =3+5 -> 8 | I11: 0 | J11: 1.85 | K11: =I11*J11 -> 0
A12: VN0108LD00007 | B12: LD00007 | C12: 7 | D12: PM2B-1LWE | E12: LEDS | F12: 0 | I12: =F12+G12-H12 -> 0 | J12: 1 | K12: =I12*J12 -> 0
A13: VN0109LD00008 | B13: LD00008 | C13: 8 | D13: NICHIA 0.5 WATT MILKY WHITE | E13: LEDS | F13: 0 | I13: =F13+G13-H13 -> 0 | J13: 1.5 | K13: =I13*J13 -> 0
A14: VN0030LD00009 | B14: LD00009 | C14: 9 | D14: 6070 HIGH POWER EDISON LEDS | E14: LEDS | F14: 0 | I14: =F14+G14-H14 -> 0 | J14: 27 | K14: =I14*J14 -> 0
A15: VN0030LD00010 | B15: LD00010 | C15: 10 | D15: 91 LED TUBE LIGHT STRIP (EDISON LED) | E15: LEDS | F15: 0 | I15: =F15+G15-H15 -> 0 | J15: 1000 | K15: =I15*J15 -> 0
A16: VN0107LD00011 | B16: LD00011 | C16: 11 | D16: LEUWD1W401 OSRAM STAR LED | E16: SAMPLES | F16: 0 | I16: =F16+G16-H16 -> 0 | J16: 45 | K16: =I16*J16 -> 0
A17: VN0107LD00012 | B17: LD00012 | C17: 12 | D17: LYG6SP-CBDB-45-1-140-R182 OSRAM LEDS | E17: SAMPLES | F17: 30 | I17: =F17+G17-H17 -> 30 | J17: 45 | K17: =I17*J17 -> 1350
A18: VN0094LD00013 | B18: LD00013 | C18: 13 | D18: LED FM-P3528WNS-460W -R80-150mA (MILKY WHITE) | E18: LED | F18: 1315 | G18: =3000+2980+15000 -> 20980 | H18: =5+3000+2975+9000+5+4+20 -> 15009 | I18: 6669 | J18: 4.35 | K18: =I18*J18 -> 29010.15
A19: VN0094LD00014 | B19: LD00014 | C19: 14 | D19: LED 5630 1CHIP 38LUM@100mA SEOUL | E19: LED | F19: 0 | I19: =F19+G19-H19 -> 0 | J19: 5 | K19: =I19*J19 -> 0
B20: LD00015 | C20: 20 | D20: FM-T3528WLS-460R -R70 | E20: LED | F20: 52 | G20: 3000 | I20: 280 | J20: 1.4 | K20: =I20*J20 -> 392
A21: VN0094LD00016 | B21: LD00016 | C21: 16 | D21: FM-3014WNS-460R | E21: LED | F21: =6000+2800 -> 8800 | I21: 8800 | J21: 1.65 | K21: =I21*J21 -> 14520
A22: VN0094LD00017 | B22: LD00017 | C22: 17 | D22: FM-3014WLS-460R-R70 | E22: LED | F22: 9000 | I22: 9000 | J22: 1.65 | K22: =I22*J22 -> 14850
B23: LD00018 | C23: 18 | D23: FM-P3528WNS-460W(150mA) | E23: LED | F23: 0 | G23: 0 | H23: 0 | I23: 0 | J23: 0 | K23: 0
B24: LD00019 | C24: 19 | D24: FM-T3528WNS-460R LEDS | E24: LED | F24: 0 | G24: 0 | H24: 0 | I24: 0 | J24: 0 | K24: 0
B25: LD00020 | C25: 20 | D25: YXG-3528EF1ZWF2 | E25: LED | F25: 2000 | H25: 104 | I25: 1800 | J25: 1.85 | K25: =I25*J25 -> 3330
B26: LD00021 | C26: 21 | D26: FM-P3528WNS-460Q(60mA) | E26: LED | F26: 745 | G26: 15000 | H26: 12043 | I26: 498805 | J26: 1.61 | K26: =J26*I26 -> 803076.05
B27: LD00022 | C27: 22 | D27: NFSW757DT | E27: LED | F27: 2000 | G27: 110 | H27: 0 | I27: 2000 | J27: 0 | K27: 0
A28: VN0094LD00015 | B28: LD00023 | C28: 23 | D28: FM-T3528WNS-460R LEDS | E28: LED | F28: 85 | H28: =10+75 -> 85 | I28: 3400 | J28: 1.85 | K28: =I28*J28 -> 6290
B29: LD00024 | C29: 24 | D29: LED FM-P3528WLS-460W -R80-150mA (WARM WHITE) | E29: LED | I29: 1200 | J29: 2.6 | K29: =I29*J29 -> 3120
J30: TOTAL | K30: =SUM(K6:K29) -> 997867.7

Sheet PCB
A2: MC PCB STORE STOCK
A4: RAWMATERIAL CODE | B4: CATAGARE NO | C4: SLNO | D4: PART NO | E4: DESCRIPTION | F4: PHY QTY | G4: RECEIPT | H4: ISSUE | I4: BALANCE | J4: UNIT PRICE | K4: AMOUNT
A5: VN0098PCB09001 | B5: PCB09001 | C5: 1 | D5: TUBE LIGHT 4.4 VER | E5: PCB | I5: =F5+G5-H5 -> 0 | J5: 9 | K5: =I5*J5 -> 0
A6: VN0098PCB09002 | B6: PCB09002 | C6: 2 | D6: E27-SEM REV 3.2 | E6: PCB | I6: =F6+G6-H6 -> 0 | J6: 6.5 | K6: =I6*J6 -> 0
A7: VN0098PCB09003 | B7: PCB09003 | C7: 3 | D7: T10-TUBE LIGHT MCPCB | E7: MC PCB | I7: =F7+G7-H7 -> 0 | J7: 15 | K7: =I7*J7 -> 0
A8: VN0098PCB09004 | B8: PCB09004 | C8: 4 | D8: T10-TUBE LIGHT MCPCB V1 | E8: MC PCB | I8: =F8+G8-H8 -> 0 | J8: 15 | K8: =I8*J8 -> 0
A9: VN0098PCB09005 | B9: PCB09005 | C9: 5 | D9: T8 TUBE LIGHT MC PCB 140 LEDS | E9: MC PCB | I9: 8000 | J9: 6 | K9: =I9*J9 -> 48000
A10: VN0098PCB09006 | B10: PCB09006 | C10: 6 | D10: T8 TUBE LIGHT MC PCB 150 LEDS | E10: MC PCB | I10: =F10+G10-H10 -> 0 | J10: 6 | K10: =I10*J10 -> 0
A11: VN0098PCB09007 | B11: PCB09007 | C11: 7 | D11: 91 LEDS -Tubelight MCPCB | E11: MC PCB | I11: =F11+G11-H11 -> 0 | J11: 410 | K11: =I11*J11 -> 0
A12: VN0098PCB09008 | B12: PCB09008 | C12: 8 | D12: T8 TUBE LIGHT MC PCB | E12: MC PCB | I12: =F12+G12-H12 -> 0 | J12: 6 | K12: =I12*J12 -> 0
A13: VN0098PCB09009 | B13: PCB09009 | C13: 9 | D13: T8 TUBE LIGHT MC PCB V1 | E13: MC PCB | I13: =F13+G13-H13 -> 0 | J13: 6 | K13: =I13*J13 -> 0
A14: VN0098PCB09010 | B14: PCB09010 | C14: 10 | D14: SEM VER 1.0 MC PCB 140LEDS | E14: MC PCB | I14: 6958 | J14: 400 | K14: =I14*J14 -> 2783200
A15: VN0098PCB09011 | B15: PCB09011 | C15: 11 | D15: SEM VER 1.0 MC PCB 120LEDS | E15: MC PCB | I15: =F15+G15-H15 -> 0 | J15: 360 | K15: =I15*J15 -> 0
A16: VN0111PCB09012 | B16: PCB09012 | C16: 12 | D16: CIRCULAR MC PCB 15LED | E16: MC PCB | I16: =F16+G16-H16 -> 0 | J16: 20 | K16: =I16*J16 -> 0
A17: VN0111PCB09013 | B17: PCB09013 | C17: 13 | D17: CIRCULAR MC PCB 10LED | E17: MC PCB | I17: =F17+G17-H17 -> 0 | J17: 20 | K17: =I17*J17 -> 0
A18: VN0111PCB09014 | B18: PCB09014 | C18: 14 | D18: 10 WATT CIRCULAR MC PCB WITH LED ASSEMBLED | E18: MC PCB | F18: =76+39 -> 115 | H18: =1+1 -> 2 | I18: =F18+G18-H18 -> 113 | J18: 230 | K18: =I18*J18 -> 25990
A19: VN0111PCB09015 | B19: PCB09015 | C19: 15 | D19: 15 WATT CIRCULAR MC PCB WITH LED ASSEMBLED | E19: MC PCB | F19: 24 | I19: =F19+G19-H19 -> 24 | J19: 340 | K19: =I19*J19 -> 8160
A20: VN0111PCB09016 | B20: PCB09016 | C20: 16 | D20: 20 WATT CIRCULAR MC PCB WITH LED ASSEMBLED | E20: MC PCB | F20: 5 | I20: =F20+G20-H20 -> 5 | J20: 410 | K20: =I20*J20 -> 2050
A21: VN0111PCB09017 | B21: PCB09017 | C21: 17 | D21: 3 WATT CIRCULAR MC PCB WITH LED ASSEMBLED(CN) | E21: MC PCB | F21: 475 | H21: =30+6 -> 36 | I21: =F21+G21-H21 -> 439 | J21: 10 | K21: =I21*J21 -> 4390
A22: VN0111PCB09018 | B22: PCB09018 | C22: 18 | D22: 5 WATT CIRCULAR MC PCB WITH LED ASSEMBLED(CN) | E22: MC PCB | F22: 166 | H22: =30+3+2+1+1+1+1 -> 39 | I22: =F22+G22-H22 -> 127 | J22: 10 | K22: =I22*J22 -> 1270
A23: VN0111PCB09019 | B23: PCB09019 | C23: 19 | D23: 9 WATT CIRCULAR MC PCB WITH LED ASSEMBLED(CN) | E23: MC PCB | I23: =F23+G23-H23 -> 0 | J23: 10 | K23: =I23*J23 -> 0
A24: VN0111PCB09020 | B24: PCB09020 | C24: 20 | D24: 15 WATT CIRCULAR MC PCB WITH LED ASSEMBLED(CN) | E24: MC PCB | I24: =F24+G24-H24 -> 0 | J24: 165 | K24: =I24*J24 -> 0
A25: VN0111PCB09021 | B25: PCB09021 | C25: 21 | D25: 3 WATT CIRCULAR MC PCB(CHINAN) | E25: MC PCB | I25: =F25+G25-H25 -> 0 | J25: 3 | K25: =I25*J25 -> 0
A26: VN0111PCB09022 | B26: PCB09022 | C26: 22 | D26: 6 WATT CIRCULAR MC PCB(CN) | E26: MC PCB | F26: 35 | I26: =F26+G26-H26 -> 35 | J26: 5 | K26: =I26*J26 -> 175
A27: VN0111PCB09023 | B27: PCB09023 | C27: 23 | D27: 18 WATT CIRCULAR MC PCB(CN) | E27: MC PCB | I27: =F27+G27-H27 -> 0 | J27: 7 | K27: =I27*J27 -> 0
A28: VN0111PCB09024 | B28: PCB09024 | C28: 24 | D28: 30 WATT CIRCULAR MC PCB (CN) | E28: MC PCB | I28: =F28+G28-H28 -> 0 | J28: 10 | K28: =I28*J28 -> 0
A29: VN0098PCB09025 | B29: PCB09025 | C29: 25 | D29: 20 Watt circular | E29: MCPCB | I29: =F29+G29-H29 -> 0 | J29: 10 | K29: =I29*J29 -> 0
A30: VN0098PCB09026 | B30: PCB09026 | C30: 26 | D30: 10 WATT CIRCULAR | E30: MCPCB | I30: =F30+G30-H30 -> 0 | J30: 10 | K30: =I30*J30 -> 0
A31: VN0098PCB09027 | B31: PCB09027 | C31: 27 | D31: 15 WATT CIRCULAR | E31: MCPCB | F31: 14 | I31: =F31+G31-H31 -> 14 | J31: 12 | K31: =I31*J31 -> 168
A32: VN0098PCB09028 | B32: PCB09028 | C32: 28 | D32: SM 18 WATT VER 4.2 | E32: BARE PCB | F32: 2160 | I32: =F32+G32-H32 -> 2160 | J32: 5 | K32: =I32*J32 -> 10800
A33: VN0070PCB09029 | B33: PCB09029 | C33: 29 | D33: SL-CONT | E33: BARE PCB | I33: =F33+G33-H33 -> 0 | J33: 5 | K33: =I33*J33 -> 0
A34: VN0070PCB09030 | B34: PCB09030 | C34: 30 | D34: E27-CS-EM1 | E34: BARE PCB | I34: =F34+G34-H34 -> 0 | J34: 6 | K34: =I34*J34 -> 0
A35: VN0098PCB09031 | B35: PCB09031 | C35: 31 | D35: T8 TUBE LIGHT MC PCB 1 FT | E35: BARE PCB | I35: =F35+G35-H35 -> 0 | J35: 6 | K35: =I35*J35 -> 0
A36: VN0111PCB09032 | B36: PCB09032 | C36: 32 | D36: 3 WATT CIRCULAR MC PCB WITH LED ASSEMBLED(CN)WW | E36: MC PCB | I36: =F36+G36-H36 -> 0 | J36: 22 | K36: =I36*J36 -> 0
A37: VN0111PCB09033 | B37: PCB09033 | C37: 33 | D37: 9 WATT CIRCULAR MC PCB WITH LED ASSEMBLED(CN)WW | E37: MC PCB | I37: =F37+G37-H37 -> 0 | J37: 28 | K37: =I37*J37 -> 0
A38: VN0111PCB09034 | B38: PCB09034 | C38: 34 | D38: 20 WATT CIRCULAR MC PCB WITH LED ASSEMBLEDWW | E38: MC PCB | I38: =F38+G38-H38 -> 0 | J38: 410 | K38: =I38*J38 -> 0
A39: VN0098PCB09035 | B39: PCB09035 | C39: 35 | D39: SM 3300 VER TL 5.8 D/S | E39: MC PCB | I39: =F39+G39-H39 -> 0 | J39: 25.92 | K39: =I39*J39 -> 0
A40: VN0098PCB09036 | B40: PCB09036 | C40: 36 | D40: SM 18 WATT VER 5.4 | E40: PCB | F40: 0 | G40: =3584+1875 -> 5459 | H40: 0 | I40: =G40-H40 -> 5459 | J40: 17.57 | K40: =I40*J40 -> 95914.63
A41: VN0098PCB09037 | B41: PCB09037 | C41: 37 | D41: SM 4-7 WATT 6300B | E41: PCB | I41: =F41+G41-H41 -> 0 | J41: 7 | K41: =I41*J41 -> 0
A42: VN0007PCB09038 | B42: PCB09038 | C42: 38 | D42: 600 MM LED PCB INTEGRATED | E42: PCB | I42: =F42+G42-H42 -> 0 | J42: 111.21 | K42: =I42*J42 -> 0
A43: VN0007PCB09039 | B43: PCB09039 | C43: 39 | D43: 1200 MM LED PCB | E43: PCB | I43: =F43+G43-H43 -> 0 | J43: 230.78 | K43: =I43*J43 -> 0
A44: VN0098PCB09040 | B44: PCB09040 | C44: 40 | D44: SEM-SURGE-VER 1.0 S/S (196 X 1 ) | E44: PCB | I44: =F44+G44-H44 -> 0 | J44: 266.36 | K44: =I44*J44 -> 0
A45: VN0098PCB09041 | B45: PCB09041 | C45: 41 | D45: SEM VER ST 1.0 -S/S METALCLAD PCB | E45: MC PCB | I45: =F45+G45-H45 -> 0 | J45: 283.26 | K45: =I45*J45 -> 0
A46: VN0098PCB09042 | B46: PCB09042 | C46: 42 | D46: 50 LED INTEGREATED PCB | E46: PCB | I46: =F46+G46-H46 -> 0 | J46: 8 | K46: =I46*J46 -> 0
A47: VN0098PCB09043 | B47: PCB09043 | C47: 43 | D47: T8 TUBE LIGHT MC PCB 140 LEDS (WARM WHITE) | E47: PCB | I47: =F47+G47-H47 -> 0 | K47: =I47*J47 -> 0
A48: VN0098PCB09044 | B48: PCB09044 | C48: 44 | D48: SEM VER 1.0 MC PCB 117 LEDS Assembled | E48: PCB | I48: =F48+G48-H48 -> 0 | K48: =I48*J48 -> 0
A49: VN0098PCB09045 | B49: PCB09045 | C49: 45 | D49: T8 TUBE LIGHT MC PCB 117 LEDS | E49: PCB | I49: =F49+G49-H49 -> 0 | K49: =I49*J49 -> 0
A50: VN0098PCB09046 | B50: PCB09046 | C50: 46 | D50: SDL XX B-ver 1.4 pcb Charges | E50: PCB | I50: =F50+G50-H50 -> 0 | K50: =I50*J50 -> 0
A51: VN0098PCB09047 | B51: PCB09047 | C51: 47 | D51: E-27-CS-REV 4.10 pcb CHARGES | E51: PCB | I51: =F51+G51-H51 -> 0 | K51: =I51*J51 -> 0
A52: VN0098PCB09048 | B52: PCB09048 | C52: 48 | D52: SUPRA ENERGY MC V2 25 LED PCB | E52: PCB | I52: =F52+G52-H52 -> 0 | J52: 250.88 | K52: =I52*J52 -> 0
A53: VN0098PCB09049 | B53: PCB09049 | C53: 49 | D53: SUPRA MC V2 PCB 25 LED ASSEMBLED | E53: PCB | I53: =F53+G53-H53 -> 0 | K53: =I53*J53 -> 0
A54: VN0098PCB09050 | B54: PCB09050 | C54: 50 | D54: 3 WATT CIRCULAR MC PCB WITH LED ASSEMBLED | E54: PCB | I54: =F54+G54-H54 -> 0 | J54: 50 | K54: =I54*J54 -> 0
A55: VN0098PCB09051 | B55: PCB09051 | C55: 51 | D55: 6 WATT CIRCULAR MC PCB WITH LED ASSEMBLED | E55: PCB | F55: =194+10 -> 204 | H55: 1 | I55: =F55+G55-H55 -> 203 | J55: 50 | K55: =I55*J55 -> 10150
A56: VN0098PCB09052 | B56: PCB09052 | C56: 52 | D56: SEMTRONICS VER DL 2.1 SM 63 X B D/S (10 X 1) | E56: PCB | I56: =F56+G56-H56 -> 0 | K56: =I56*J56 -> 0
B57: PCB09053 | C57: 53 | D57: PCB 5.8VERSION S/S TL DRIVER | E57: BARE PCB | I57: =F57+G57-H57 -> 0 | K57: =I57*J57 -> 0
B58: PCB09054 | C58: 54 | D58: MC PCB 3.5WATT VER 2.0 (WW) | E58: MCPCB | F58: 20 | I58: =F58+G58-H58 -> 20 | J58: 8 | K58: =I58*J58 -> 160
B59: PCB09055 | C59: 55 | D59: MC PCB 7 WATT VER 18-0 | E59: MCPCB | F59: 445 | I59: =F59+G59-H59 -> 445 | J59: 8 | K59: =I59*J59 -> 3560
B60: PCB09056 | C60: 56 | D60: SM 18 WATT VER 5.1 DRIVER PCB | E60: PCB | F60: 402 | I60: =F60+G60-H60 -> 402 | J60: 7 | K60: =I60*J60 -> 2814
B61: PCB09057 | C61: 57 | D61: SM ISO REV 2.1 PCB | E61: PCB | F61: 710 | I61: =F61+G61-H61 -> 710 | J61: 6.5 | K61: =I61*J61 -> 4615
B62: PCB09058 | C62: 58 | D62: SEM VER TL 5.8 DRIVER BOARD | E62: PCB | F62: 1963 | I62: 4000 | J62: 12 | K62: =I62*J62 -> 48000
B63: PCB09059 | C63: 59 | D63: PCB SEM VER 4.1 LED PCB 117 LED | E63: PCB | F63: 248 | H63: =1+1+1 -> 3 | I63: =F63+G63-H63 -> 245 | J63: 11 | K63: =I63*J63 -> 2695
B64: PCB09060 | C64: 60 | D64: PCB SEM VER TL 1.0 LED PCB 140 LED | E64: PCB | F64: =73+603 -> 676 | G64: 50 | H64: =1+10+10+2+11+2+2+4+100+4 -> 146 | I64: =F64+G64-H64 -> 580 | J64: 9.5 | K64: =I64*J64 -> 5510
B65: PCB09061 | C65: 61 | D65: PCB 2835LED25C4B1170X9.8B/O | E65: PCB | F65: 572 | I65: =F65+G65-H65 -> 572 | J65: 8 | K65: =I65*J65 -> 4576
B66: PCB09062 | C66: 62 | D66: PCB 2835LED12C4B538X9.5A/O | E66: PCB | F66: 29 | I66: =F66+G66-H66 -> 29 | J66: 10 | K66: =I66*J66 -> 290
B67: PCB09063 | C67: 63 | D67: PCB 9630145569.9 | E67: PCB | F67: 5 | I67: =F67+G67-H67 -> 5 | J67: 11 | K67: =I67*J67 -> 55
B68: PCB09064 | C68: 64 | D68: PCB 555X7MM 3014LED 12C15B | E68: PCB | F68: 12 | I68: =F68+G68-H68 -> 12 | J68: 17 | K68: =I68*J68 -> 204
B69: PCB09065 | C69: 65 | D69: PCB 255X7MM 3014 LED 12C6B | E69: PCB | F69: 7 | I69: =F69+G69-H69 -> 7 | J69: 18 | K69: =I69*J69 -> 126
B70: PCB09066 | C70: 66 | D70: PCB STRIP LIGHT | E70: PCB | F70: 53 | I70: =F70+G70-H70 -> 53 | J70: 15 | K70: =I70*J70 -> 795
B71: PCB09067 | D71: PCB SM 63XX8 VER 2.1DL | E71: PCB | F71: 514 | I71: =F71+G71-H71 -> 514 | J71: 8 | K71: =I71*J71 -> 4112
B72: PCB09068 | C72: 68 | D72: SEM -VER LED 1MM S/S WHITE MASK ROUND PCB | E72: PCB | F72: 0 | G72: 68 | H72: 68 | I72: =F72+G72-H72 -> 0 | K72: =I72*J72 -> 0
B73: PCB09069 | C73: 69 | D73: SEM VER TL 6.3 (52 LED) S/S PCB | E73: PCB | F73: 0 | G73: 0 | H73: 0 | I73: 0 | J73: 7 | K73: =I73*J73 -> 0
B74: PCB09070 | D74: SEM VER TL 6.3 (52 LED) S/S PCB WITH LED 60MA | E74: PCB | F74: 0 | G74: =25+97 -> 122 | H74: 25 | I74: =F74+G74-H74 -> 97 | K74: =I74*J74 -> 0
B75: PCB09071 | C75: 71 | D75: SEM -VER LED 1MM S/S WHITE MASK ROUND PCB 9W 2P 9S (LED ASSEMBLED ) | E75: PCB | F75: 0 | G75: =25+124 -> 149 | H75: =2+5+16+2 -> 25 | I75: =F75+G75-H75 -> 124 | K75: =I75*J75 -> 0
B76: PCB09072 | C76: 72 | D76: SSTxxB-VER DL 1.9 | E76: PCB | F76: 0 | G76: 0 | H76: 0 | I76: 0 | J76: 0 | K76: 0
B77: PCB09073 | C77: 73 | D77: SM 18 WATT VER 5.13 DRIVER PCB | E77: PCB | F77: 0 | G77: 0 | H77: 0 | I77: 0 | J77: 0 | K77: 0
B78: PCB09074 | C78: 74 | D78: 3 WATT CIRCULAR MC PCB WITH LED ASSEMBLED(SPOT LIGHT)CN | E78: PCBA | F78: 0 | G78: 0 | H78: 0 | I78: 0 | J78: 0 | K78: 0
B79: PCB09075 | C79: 75 | D79: VER DL ES 02 (34mm*82mm) | E79: PCB | F79: 0 | G79: 0 | H79: 0 | I79: 0 | J79: 0 | K79: 0
B80: PCB09076 | C80: 76 | D80: SEM VER T15.8-D/S PCB | E80: PCB | F80: 0 | G80: 0 | H80: 0 | I80: 0 | J80: 0 | K80: 0
B81: PCB09077 | C81: 77 | D81: SEM VER TLLP 3528 4.0-S/S (13 X 1 ) WHITE MASK PCB | E81: PCB | F81: 0 | G81: 0 | H81: 0 | I81: 0 | J81: 0 | K81: 0
B82: PCB09078 | C82: 78 | D82: SSTXX B-VERST-1.12 D/S(8 X 1) | E82: PCB | F82: 0 | G82: 0 | H82: 0 | I82: 0 | J82: 0 | K82: 0
B83: PCB09079 | C83: 79 | D83: 6 WATT MC PCB(UNIVERSAL) | E83: PCB | F83: 0 | G83: 0 | H83: 0 | I83: 0 | J83: 0 | K83: 0
B84: PCB09080 | C84: 80 | D84: VER SDR 26 XXA 1.0 S/S (60 X 1) | E84: PCB | F84: 0 | G84: 5159 | H84: 0 | I84: =F84+G84-H84 -> 5159 | J84: 1.5 | K84: =I84*J84 -> 7738.5
B85: PCB09081 | C85: 67 | D85: SEM 1.0 | E85: PCB | F85: 2640 | I85: =F85+G85-H85 -> 2640 | J85: 5 | K85: =I85*J85 -> 13200
B86: PCB09082 | C86: 71 | D86: SEM VER TL 6.3 (52 LED) S/S PCB WITH LED 150MA | E86: PCB | F86: 0 | G86: =25+124 -> 149 | H86: =2+5+16+2 -> 25 | I86: =F86+G86-H86 -> 124 | K86: =I86*J86 -> 0
B87: PCB09083 | C87: 72 | D87: PCB AMOU 0477 CIRCULAR | E87: MC PCB | G87: 249 | H87: 245 | I87: =F87+G87-H87 -> 4 | K87: =I87*J87 -> 0
B88: PCB09084 | C88: 73 | D88: SDLXXB-VER BL1.5 | E88: BARE PCB | F88: 0 | G88: 2040 | H88: 2010 | I88: =F88+G88-H88 -> 30 | J88: 5.7 | K88: =I88*J88 -> 171
B89: PCB09085 | C89: 74 | D89: PCB AN3088 BUCK BOOST DOUBLE SIDED | E89: BARE PCB | F89: 0 | G89: 9 | H89: 0 | I89: =F89+G89-H89 -> 9 | K89: =I89*J89 -> 0
B90: PCB09086 | C90: 75 | D90: PCB VERT 3528 -SINGLE SIDED WHITE MASK | E90: BARE PCB | F90: 0 | G90: 9 | H90: 0 | I90: =F90+G90-H90 -> 9 | K90: =I90*J90 -> 0
B91: PCB09087 | C91: 76 | D91: VER SDR 26 XXA 1.0 S/S (60 X 1) | F91: 0 | G91: 5159 | H91: 0 | I91: =F91+G91-H91 -> 5159 | J91: 1.5 | K91: =I91*J91 -> 7738.5
B92: PCB09088 | C92: 77 | D92: PCB VER DLES 02 | E92: PCB | F92: 0 | G92: =3107+2961 -> 6068 | I92: =3107+2961 -> 6068 | J92: 8.4 | K92: =I92*J92 -> 50971.2
B93: PCB09089 | D93: SEM VER TL 6.3 (52 LED) S/S PCB WITH LED 150MA | E93: PCB | F93: 0 | G93: =25+124 -> 149 | H93: =2+5+16+2 -> 25 | I93: =F93+G93-H93 -> 124 | K93: =I93*J93 -> 0
J94: TOTAL | K94: =SUM(K5:K93) -> 3147598.8

Sheet RESISTOR
D2: RESISTER STORE STOCK
D4: RAWMATERIAL CODE | E4: CATAGARE NO | F4: SLNO | G4: PART NO | H4: DESCRIPTION | I4: PHYSICAL QTY | J4: RECEIPT | K4: ISSUE | L4: BALANCE | M4: UNIT PRICE | N4: AMOUNT
D5: VN0089RS01001 | E5: RS01001 | F5: 1 | G5: 33K/0603/5% | H5: SMD RESISTOR | I5: 300 | L5: =I5+J5-K5 -> 300 | M5: 0.15 | N5: =L5*M5 -> 45
D6: VN0089RS01002 | E6: RS01002 | F6: 2 | G6: 100PF/0805/ 50V /5% | H6: SMD CAPACITOR | I6: 4688 | K6: =10+702+180+35+25+1000+5 -> 1957 | L6: =I6+J6-K6 -> 2731 | M6: 0.6 | N6: =L6*M6 -> 1638.6
D7: VN0089RS01003 | E7: RS01003 | F7: 3 | G7: 432E/0603/1% | H7: SMD RESISTOR | L7: =I7+J7-K7 -> 0 | M7: 0.1 | N7: =L7*M7 -> 0
D8: VN0089RS01004 | E8: RS01004 | F8: 4 | G8: 200K/0603/1% | H8: SMD RESISTOR | I8: 300 | L8: =I8+J8-K8 -> 300 | M8: 0.1 | N8: =L8*M8 -> 30
D9: VN0089RS01005 | E9: RS01005 | F9: 5 | G9: 10E/0603/1% | H9: SMD RESISTOR | L9: =I9+J9-K9 -> 0 | M9: 0.04 | N9: =L9*M9 -> 0
D10: VN0089RS01006 | E10: RS01006 | F10: 6 | G10: 1UF/0805/10% 25 V OR 50V | H10: SMD CAPACITOR | I10: =1000+400+6000 -> 7400 | J10: =2000+1000+8000 -> 11000 | K10: =20+400+702+702+50+1000+2000+10 -> 4884 | L10: =I10+J10-K10 -> 13516 | M10: 0.35 | N10: =L10*M10 -> 4730.6
D11: VN0089RS01007 | E11: RS01007 | F11: 7 | G11: 100K/0603/1% | H11: SMD RESISTOR | L11: =I11+J11-K11 -> 0 | M11: 0.06 | N11: =L11*M11 -> 0
D12: VN0089RS01008 | E12: RS01008 | F12: 8 | G12: MD7S/SO | H12: SMD RESISTOR | L12: =I12+J12-K12 -> 0 | M12: 5.9 | N12: =L12*M12 -> 0
D13: VN0089RS01009 | E13: RS01009 | F13: 9 | G13: 0E/0805 / 5% | H13: SMD RESISTOR | I13: 7090 | J13: 5000 | K13: =10+702+1000+5 -> 1717 | L13: =I13+J13-K13 -> 10373 | M13: 0.04 | N13: =L13*M13 -> 414.92
D14: VN0089RS01010 | E14: RS01010 | F14: 10 | G14: 1E/1206/1% | H14: SMD RESISTOR | I14: 290 | J14: 1000 | K14: 1000 | L14: =I14+J14-K14 -> 290 | M14: 0.1 | N14: =L14*M14 -> 29
D15: VN0089RS01011 | E15: RS01011 | F15: 11 | G15: 330E/1206/1% | H15: SMD RESISTOR | L15: =I15+J15-K15 -> 0 | M15: 0.05 | N15: =L15*M15 -> 0
D16: VN0089RS01012 | E16: RS01012 | F16: 12 | G16: 1UF/0805/25v | H16: SMD RESISTOR | L16: =I16+J16-K16 -> 0 | M16: 1.1 | N16: =L16*M16 -> 0
D17: VN0089RS01013 | E17: RS01013 | F17: 13 | G17: 9.53K/0805/1% | H17: SMD RESISTOR | I17: 1300 | L17: =I17+J17-K17 -> 1300 | M17: 0.07 | N17: =L17*M17 -> 91
D18: VN0089RS01014 | E18: RS01014 | F18: 14 | G18: 68.1K/0805/1% | H18: SMD RESISTOR | I18: 1000 | L18: =I18+J18-K18 -> 1000 | M18: 0.07 | N18: =L18*M18 -> 70
D19: VN0089RS01015 | E19: RS01015 | F19: 15 | G19: 15K/1206/1% | H19: SMD RESISTOR | I19: 1500 | L19: =I19+J19-K19 -> 1500 | M19: 0.07 | N19: =L19*M19 -> 105
D20: VN0089RS01016 | E20: RS01016 | F20: 16 | G20: SM4007/MELF(1A/1KV) | H20: SMD RESISTOR | L20: =I20+J20-K20 -> 0 | M20: 0.65 | N20: =L20*M20 -> 0
D21: VN0089RS01017 | E21: RS01017 | F21: 17 | G21: 332K/1206/1% | H21: SMD RESISTOR | I21: 1500 | L21: =I21+J21-K21 -> 1500 | M21: 0.04 | N21: =L21*M21 -> 60
D22: VN0089RS01018 | E22: RS01018 | F22: 18 | G22: 7.5K/1206/1% | H22: SMD RESISTOR | I22: 0 | J22: 10000 | L22: =I22+J22-K22 -> 10000 | M22: 0.07 | N22: =L22*M22 -> 700
D23: VN0089RS01019 | E23: RS01019 | F23: 19 | G23: FSM 106-TMELF UF4003 | H23: SMD RESISTOR | L23: =I23+J23-K23 -> 0 | M23: 0.65 | N23: =L23*M23 -> 0
D24: VN0089RS01020 | E24: RS01020 | F24: 20 | G24: 1M/0805 / 1% | H24: SMD RESISTOR | I24: 5000 | L24: =I24+J24-K24 -> 5000 | M24: 1 | N24: =L24*M24 -> 5000
D25: VN0089RS01021 | E25: RS01021 | F25: 21 | G25: 100K/0603 | H25: SMD RESISTOR | L25: =I25+J25-K25 -> 0 | M25: 0.06 | N25: =L25*M25 -> 0
D26: VN0089RS01022 | E26: RS01022 | F26: 22 | G26: 100R/0805/1% | H26: SMD RESISTOR | I26: 280 | L26: =I26+J26-K26 -> 280 | M26: 0.05 | N26: =L26*M26 -> 14
D27: VN0089RS01023 | E27: RS01023 | F27: 23 | G27: 10K/0603/1 % | H27: SMD RESISTOR | L27: =I27+J27-K27 -> 0 | M27: 0.05 | N27: =L27*M27 -> 0
D28: VN0089RS01024 | E28: RS01024 | F28: 24 | G28: 1M/0805/1% | H28: SMD RESISTOR | L28: =I28+J28-K28 -> 0 | M28: 0.06 | N28: =L28*M28 -> 0
D29: VN0089RS01025 | E29: RS01025 | F29: 25 | G29: 100E/0805/1% | H29: SMD RESISTOR | I29: 2600 | L29: =I29+J29-K29 -> 2600 | M29: 0.04 | N29: =L29*M29 -> 104
D30: VN0089RS01026 | E30: RS01026 | F30: 26 | G30: 10K/1206/1% | H30: SMD RESISTOR | I30: 5250 | J30: 5000 | L30: =I30+J30-K30 -> 10250 | M30: 0.06 | N30: =L30*M30 -> 615
D31: VN0089RS01027 | E31: RS01027 | F31: 27 | G31: 49.9K/0603/1% | H31: SMD RESISTOR | I31: 450 | L31: =I31+J31-K31 -> 450 | M31: 0.06 | N31: =L31*M31 -> 27
D32: VN0089RS01028 | E32: RS01028 | F32: 28 | G32: 390E/0603/1% | H32: SMD RESISTOR | L32: =I32+J32-K32 -> 0 | M32: 0.05 | N32: =L32*M32 -> 0
D33: VN0089RS01029 | E33: RS01029 | F33: 29 | G33: 150R/1206/1% | H33: SMD RESISTOR | I33: 50 | L33: =I33+J33-K33 -> 50 | M33: 0.05 | N33: =L33*M33 -> 2.5
D34: VN0089RS01030 | E34: RS01030 | F34: 30 | G34: 430R/0603/1% | H34: SMD RESISTOR | L34: =I34+J34-K34 -> 0 | M34: 0.05 | N34: =L34*M34 -> 0
D35: VN0089RS01031 | E35: RS01031 | F35: 31 | G35: 510K/0603/1% | H35: SMD RESISTOR | L35: =I35+J35-K35 -> 0 | M35: 0.06 | N35: =L35*M35 -> 0
D36: VN0089RS01032 | E36: RS01032 | F36: 32 | G36: 1.5K/0805/1% | H36: SMD RESISTOR | L36: =I36+J36-K36 -> 0 | M36: 0.06 | N36: =L36*M36 -> 0
D37: VN0089RS01033 | E37: RS01033 | F37: 33 | G37: 100K/0805/1% | H37: SMD RESISTOR | I37: 60 | J37: 700 | K37: =702+5 -> 707 | L37: 5000 | M37: 0.05 | N37: =L37*M37 -> 250
D38: VN0089RS01034 | E38: RS01034 | F38: 34 | G38: 330E/ 0603/ 1% | H38: SMD RESISTOR | I38: 1200 | L38: =I38+J38-K38 -> 1200 | M38: 0.05 | N38: =L38*M38 -> 60
D39: VN0089RS01035 | E39: RS01035 | F39: 35 | G39: 200K/0603/1% | H39: SMD RESISTOR | L39: =I39+J39-K39 -> 0 | M39: 0.06 | N39: =L39*M39 -> 0
D40: VN0089RS01036 | E40: RS01036 | F40: 36 | G40: 1.8MEG/0805/1% | H40: SMD RESISTOR | L40: =I40+J40-K40 -> 0 | M40: 0.06 | N40: =L40*M40 -> 0
D41: VN0089RS01037 | E41: RS01037 | F41: 37 | G41: 0R/0603/1% | H41: SMD RESISTOR | L41: =I41+J41-K41 -> 0 | M41: 0.06 | N41: =L41*M41 -> 0
D42: VN0089RS01038 | E42: RS01038 | F42: 38 | G42: 3K/1206/1% | H42: SMD RESISTOR | I42: 95 | L42: =I42+J42-K42 -> 95 | M42: 0.05 | N42: =L42*M42 -> 4.75
D43: VN0089RS01039 | E43: RS01039 | F43: 39 | G43: 10K/0603/1% | H43: SMD RESISTOR | I43: 2100 | L43: =I43+J43-K43 -> 2100 | M43: 0.05 | N43: =L43*M43 -> 105
D44: VN0089RS01040 | E44: RS01040 | F44: 40 | G44: 68.1K/1206/1% | H44: SMD RESISTOR | I44: 500 | L44: =I44+J44-K44 -> 500 | M44: 0.05 | N44: =L44*M44 -> 25
D45: VN0089RS01041 | E45: RS01041 | F45: 41 | G45: 150K/0603/1% | H45: SMD RESISTOR | L45: =I45+J45-K45 -> 0 | M45: 0.05 | N45: =L45*M45 -> 0
D46: VN0089RS01042 | E46: RS01042 | F46: 42 | G46: 10R/0603/1% | H46: SMD RESISTOR | I46: 100 | L46: =I46+J46-K46 -> 100 | M46: 0.05 | N46: =L46*M46 -> 5
D47: VN0089RS01043 | E47: RS01043 | F47: 43 | G47: 100K/0603/1% | H47: SMD RESISTOR | I47: 2375 | K47: 1000 | L47: =I47+J47-K47 -> 1375 | M47: 0.05 | N47: =L47*M47 -> 68.75
D48: VN0089RS01044 | E48: RS01044 | F48: 44 | G48: 240K/0805/1% | H48: SMD RESISTOR | L48: =I48+J48-K48 -> 0 | M48: 0.05 | N48: =L48*M48 -> 0
D49: VN0089RS01045 | E49: RS01045 | F49: 45 | G49: MFD/0805 | H49: SMD RESISTOR | L49: =I49+J49-K49 -> 0 | M49: 0.06 | N49: =L49*M49 -> 0
D50: VN0089RS01046 | E50: RS01046 | F50: 46 | G50: 430E/0603/1% | H50: SMD RESISTOR | I50: 7000 | J50: 5000 | K50: =1+1000 -> 1001 | L50: =I50+J50-K50 -> 10999 | M50: 0.05 | N50: =L50*M50 -> 549.95
D51: VN0089RS01047 | E51: RS01047 | F51: 47 | G51: 100PF/0805/1% | H51: SMD RESISTOR | L51: =I51+J51-K51 -> 0 | M51: 0.39 | N51: =L51*M51 -> 0
D52: VN0089RS01048 | E52: RS01048 | F52: 48 | G52: 510K/0805/1% | H52: SMD RESISTOR | I52: 0 | J52: 700 | K52: 700 | L52: =I52+J52-K52 -> 0 | M52: 0.1 | N52: =L52*M52 -> 0
D53: VN0089RS01049 | E53: RS01049 | F53: 49 | G53: 150K/0603/1% | H53: SMD RESISTOR | L53: =I53+J53-K53 -> 0 | M53: 0.05 | N53: =L53*M53 -> 0
D54: VN0089RS01050 | E54: RS01050 | F54: 50 | G54: 2A102K | H54: SMD RESISTOR | L54: =I54+J54-K54 -> 0 | M54: 1 | N54: =L54*M54 -> 0
D55: VN0089RS01051 | E55: RS01051 | F55: 51 | G55: 1MF/50V | H55: SMD RESISTOR | L55: =I55+J55-K55 -> 0 | M55: 0.85 | N55: =L55*M55 -> 0
D56: VN0089RS01052 | E56: RS01052 | F56: 52 | G56: 24.9K/1206/1% | H56: SMD RESISTOR | I56: 96 | L56: =I56+J56-K56 -> 96 | M56: 0.18 | N56: =L56*M56 -> 17.28
D57: VN0089RS01053 | E57: RS01053 | F57: 53 | G57: 0E/0603/1% | H57: SMD RESISTOR | L57: =I57+J57-K57 -> 0 | M57: 0.09 | N57: =L57*M57 -> 0
D58: VN0089RS01054 | E58: RS01054 | F58: 54 | G58: 160PF/0603/1% | H58: SMD RESISTOR | L58: =I58+J58-K58 -> 0 | M58: 0.06 | N58: =L58*M58 -> 0
D59: VN0089RS01055 | E59: RS01055 | F59: 55 | G59: 20E/1206/1% | H59: SMD RESISTOR | I59: 185 | L59: =I59+J59-K59 -> 185 | M59: 0.06 | N59: =L59*M59 -> 11.1
D60: VN0089RS01056 | E60: RS01056 | F60: 56 | G60: 10K/0603/1 % | H60: SMD RESISTOR | L60: =I60+J60-K60 -> 0 | M60: 0.05 | N60: =L60*M60 -> 0
D61: VN0089RS01057 | E61: RS01057 | F61: 57 | G61: 1M/0805/1% | H61: SMD RESISTOR | L61: =I61+J61-K61 -> 0 | M61: 0.06 | N61: =L61*M61 -> 0
D62: VN0089RS01058 | E62: RS01058 | F62: 58 | G62: 100E/0805/1% | H62: SMD RESISTOR | L62: =I62+J62-K62 -> 0 | M62: 0.04 | N62: =L62*M62 -> 0
D63: VN0089RS01059 | E63: RS01059 | F63: 59 | G63: 10K/1206/1% | H63: SMD RESISTOR | L63: =I63+J63-K63 -> 0 | M63: 0.06 | N63: =L63*M63 -> 0
D64: VN0089RS01060 | E64: RS01060 | F64: 60 | G64: 49.9K/0603/1% | H64: SMD RESISTOR | I64: 0 | J64: =1000+5000 -> 6000 | K64: 1000 | L64: =I64+J64-K64 -> 5000 | M64: 0.06 | N64: =L64*M64 -> 300
D65: VN0089RS01061 | E65: RS01061 | F65: 61 | G65: 390E/0603/1% | H65: SMD RESISTOR | I65: 300 | K65: 1 | L65: =I65+J65-K65 -> 299 | M65: 0.05 | N65: =L65*M65 -> 14.95
D66: VN0089RS01062 | E66: RS01062 | F66: 62 | G66: 150R/1206/1% | H66: SMD RESISTOR | L66: =I66+J66-K66 -> 0 | M66: 0.05 | N66: =L66*M66 -> 0
D67: VN0089RS01063 | E67: RS01063 | F67: 63 | G67: 430E/0805/1% | H67: SMD RESISTOR | I67: 0 | J67: 700 | K67: 700 | L67: =I67+J67-K67 -> 0 | M67: 0.1 | N67: =L67*M67 -> 0
D68: VN0089RS01064 | E68: RS01064 | F68: 64 | G68: 510K/0603/1% | H68: SMD RESISTOR | L68: =I68+J68-K68 -> 0 | M68: 0.06 | N68: =L68*M68 -> 0
D69: VN0089RS01065 | E69: RS01065 | F69: 65 | G69: 1.5K/0805/1% | H69: SMD RESISTOR | L69: =I69+J69-K69 -> 0 | M69: 0.06 | N69: =L69*M69 -> 0
D70: VN0089RS01066 | E70: RS01066 | F70: 66 | G70: 100K/0805/1% | H70: SMD RESISTOR | L70: =I70+J70-K70 -> 0 | M70: 0.06 | N70: =L70*M70 -> 0
D71: VN0089RS01067 | E71: RS01067 | F71: 67 | G71: 330E/ | H71: SMD RESISTOR | L71: =I71+J71-K71 -> 0 | M71: 0.05 | N71: =L71*M71 -> 0
D72: VN0089RS01068 | E72: RS01068 | F72: 68 | G72: 200K/0603/1% | H72: SMD RESISTOR | L72: =I72+J72-K72 -> 0 | M72: 0.06 | N72: =L72*M72 -> 0
D73: VN0089RS01069 | E73: RS01069 | F73: 69 | G73: 1.8MEG/0805/1% | H73: SMD RESISTOR | L73: =I73+J73-K73 -> 0 | M73: 0.06 | N73: =L73*M73 -> 0
D74: VN0089RS01070 | E74: RS01070 | F74: 70 | G74: 0E/0805/1% | H74: SMD RESISTOR | I74: 0 | J74: 700 | L74: =I74+J74-K74 -> 700 | M74: 0.1 | N74: =L74*M74 -> 70
D75: VN0089RS01071 | E75: RS01071 | F75: 71 | G75: 3K/1206/1% | H75: SMD RESISTOR | L75: =I75+J75-K75 -> 0 | M75: 0.05 | N75: =L75*M75 -> 0
D76: VN0089RS01072 | E76: RS01072 | F76: 72 | G76: 10K/0603/1% | H76: SMD RESISTOR | L76: =I76+J76-K76 -> 0 | M76: 0.05 | N76: =L76*M76 -> 0
D77: VN0089RS01073 | E77: RS01073 | F77: 73 | G77: 68.1K/1206/1% | H77: SMD RESISTOR | L77: =I77+J77-K77 -> 0 | M77: 0.05 | N77: =L77*M77 -> 0
D78: VN0089RS01074 | E78: RS01074 | F78: 74 | G78: 150K/0603/1% | H78: SMD RESISTOR | L78: =I78+J78-K78 -> 0 | M78: 0.05 | N78: =L78*M78 -> 0
D79: VN0089RS01075 | E79: RS01075 | F79: 75 | G79: 10R/0603/1% | H79: SMD RESISTOR | I79: 0 | J79: 1000 | K79: 1000 | L79: =I79+J79-K79 -> 0 | M79: 0.05 | N79: =L79*M79 -> 0
D80: VN0089RS01076 | E80: RS01076 | F80: 76 | G80: 100K/0603/1% | H80: SMD RESISTOR | I80: 480 | L80: =I80+J80-K80 -> 480 | M80: 0.05 | N80: =L80*M80 -> 24
D81: VN0089RS01077 | E81: RS01077 | F81: 77 | G81: 240K/0805/1% | H81: SMD RESISTOR | L81: =I81+J81-K81 -> 0 | M81: 0.05 | N81: =L81*M81 -> 0
D82: VN0089RS01078 | E82: RS01078 | F82: 78 | G82: MFD/0805 | H82: SMD RESISTOR | L82: =I82+J82-K82 -> 0 | M82: 0.06 | N82: =L82*M82 -> 0
D83: VN0089RS01079 | E83: RS01079 | F83: 79 | G83: 430E/0603/1% | H83: SMD RESISTOR | I83: 700 | L83: =I83+J83-K83 -> 700 | M83: 0.05 | N83: =L83*M83 -> 35
D84: VN0089RS01080 | E84: RS01080 | F84: 80 | G84: 100PF/0805/1% | H84: SMD RESISTOR | L84: =I84+J84-K84 -> 0 | M84: 0.39 | N84: =L84*M84 -> 0
D85: VN0089RS01081 | E85: RS01081 | F85: 81 | G85: 510K/0805/1% | H85: SMD RESISTOR | L85: =I85+J85-K85 -> 0 | M85: 0.05 | N85: =L85*M85 -> 0
D86: VN0089RS01082 | E86: RS01082 | F86: 82 | G86: 150K/0603/1% | H86: SMD RESISTOR | I86: 100 | L86: =I86+J86-K86 -> 100 | M86: 0.05 | N86: =L86*M86 -> 5
D87: VN0089RS01083 | E87: RS01083 | F87: 83 | G87: 2A102K | H87: SMD RESISTOR | L87: =I87+J87-K87 -> 0 | M87: 1 | N87: =L87*M87 -> 0
D88: VN0089RS01084 | E88: RS01084 | F88: 84 | G88: 1MF/50V | H88: SMD RESISTOR | L88: =I88+J88-K88 -> 0 | M88: 0.85 | N88: =L88*M88 -> 0
D89: VN0089RS01085 | E89: RS01085 | F89: 85 | G89: 24.9K/1206/1% | H89: SMD RESISTOR | L89: =I89+J89-K89 -> 0 | M89: 0.18 | N89: =L89*M89 -> 0
D90: VN0089RS01086 | E90: RS01086 | F90: 86 | G90: 0E/0603/1% | H90: SMD RESISTOR | L90: =I90+J90-K90 -> 0 | M90: 0.09 | N90: =L90*M90 -> 0
D91: VN0089RS01087 | E91: RS01087 | F91: 87 | G91: 160PF/0603/1% | H91: SMD RESISTOR | L91: =I91+J91-K91 -> 0 | M91: 0.06 | N91: =L91*M91 -> 0
D92: VN0089RS01088 | E92: RS01088 | F92: 88 | G92: 20E/0805/1% | H92: SMD RESISTOR | L92: =I92+J92-K92 -> 0 | M92: 0.06 | N92: =L92*M92 -> 0
D93: VN0089RS01089 | E93: RS01089 | F93: 89 | G93: 1.5E/1206/1% | H93: SMD RESISTOR | I93: 14000 | L93: =I93+J93-K93 -> 14000 | M93: 0.28 | N93: =L93*M93 -> 3920
D94: VN0089RS01090 | E94: RS01090 | F94: 90 | G94: 332K/0805/1% | H94: SMD RESISTOR | I94: 5000 | L94: =I94+J94-K94 -> 5000 | M94: 0.08 | N94: =L94*M94 -> 400
D95: VN0089RS01091 | E95: RS01091 | F95: 91 | G95: 100nF/0805 / 5% | H95: SMD CAPACITOR | I95: 11985 | K95: 1000 | L95: =I95+J95-K95 -> 10985 | M95: 0.29 | N95: =L95*M95 -> 3185.65
D96: VN0089RS01092 | E96: RS01092 | F96: 92 | G96: 49.9K/0805/1% | H96: SMD RESISTOR | I96: 0 | J96: 2000 | K96: 2000 | L96: 5000 | M96: 0.15 | N96: =L96*M96 -> 750
D97: VN0089RS01093 | E97: RS01093 | F97: 93 | G97: 680K/0603 / 1% | H97: SMD RESISTORE | I97: 0 | J97: 5000 | K97: 1000 | L97: =I97+J97-K97 -> 4000 | M97: 0.05 | N97: =L97*M97 -> 200
D98: VN0009RS01094 | E98: RS01094 | F98: 94 | G98: 174K/0603/ 1% | H98: SMD RESISTORE | I98: 0 | J98: =700+5000+5000 -> 10700 | K98: 700 | L98: =I98+J98-K98 -> 10000 | M98: 0.05 | N98: =L98*M98 -> 500
D99: VN0089RS01095 | E99: RS01095 | F99: 95 | G99: 1K/0603 / 1% | H99: SMD RESISTORE | I99: 500 | J99: 700 | K99: 700 | L99: =I99+J99-K99 -> 500 | M99: 0.1 | N99: =L99*M99 -> 50
D100: VN0009RS01096 | E100: RS01096 | F100: 96 | G100: 0.68E/1206 / 1% | H100: SMD RESISTORE | I100: 15000 | J100: 10000 | K100: =20+1404+180+2+1000+10 -> 2616 | L100: =I100+J100-K100 -> 22384 | M100: 1.8 | N100: =L100*M100 -> 40291.2
D101: VN0089RS01097 | E101: RS01097 | F101: 97 | G101: 680K/1206 / 1% | H101: SMD RESISTORE | I101: 0 | J101: =800+4000 -> 4800 | K101: =800+4000 -> 4800 | L101: =I101+J101-K101 -> 0 | M101: 0.12 | N101: =L101*M101 -> 0
D102: VN0089RS01098 | E102: RS01098 | F102: 98 | G102: 110K/1206 / 1% | H102: SMD RESISTORE | I102: 600 | J102: 400 | K102: 400 | L102: =I102+J102-K102 -> 600 | M102: 0.12 | N102: =L102*M102 -> 72
...

Sheet CONNECTOR
A3: CONNUCTOR STORE STOCK
A5: RAWMATERIAL CODE | B5: CATAGARE NO | C5: SLNO | D5: PART NO | E5: DESCRIPTION | F5: PHY QTY | G5: RECEIPT | H5: ISSUE | I5: BALANCE | J5: UNIT PRICE | K5: AMOUNT
A6: VN0031CR18001 | B6: CR18001 | C6: 1 | D6: 2 Pin Ac connector | E6: connector | F6: 0 | I6: =F6+G6-H6 -> 0 | J6: 10 | K6: =I6*J6 -> 0
A7: VN0031CR18002 | B7: CR18002 | C7: 2 | D7: 2 Pin CPU + PIN MALE | E7: connuctor | F7: 0 | I7: =F7+G7-H7 -> 0 | J7: 1.5 | K7: =I7*J7 -> 0
A8: VN0031CR18003 | B8: CR18003 | C8: 3 | D8: 2 Pin CPU + PIN FEMALE | E8: connuctor | F8: 0 | I8: =F8+G8-H8 -> 0 | J8: 1.5 | K8: =I8*J8 -> 0
A9: VN0031CR18004 | B9: CR18004 | C9: 4 | D9: 5 Pin Ac connector | E9: connuctor | F9: 0 | I9: =F9+G9-H9 -> 0 | J9: 10 | K9: =I9*J9 -> 0
B10: CR18005 | C10: 5 | D10: 2 PIN PBT CONNECTOR | E10: CONNECTOR | F10: 0 | G10: =2000+1000+4000 -> 7000 | I10: =F10+G10-H10 -> 7000 | J10: 2.5 | K10: =I10*J10 -> 17500
B11: CR18006 | C11: 6 | D11: 3 PIN PBT CONNECTOR | E11: CONNECTOR | F11: 0 | G11: =2400+1200+3800 -> 7400 | I11: =F11+G11-H11 -> 7400 | J11: 3.75 | K11: =I11*J11 -> 27750
B12: CR18007 | C12: 7 | D12: 1A, 250V Slow Blow | E12: FUSE | F12: 0 | G12: 4800 | I12: =F12+G12-H12 -> 4800 | J12: 2.5 | K12: =I12*J12 -> 12000
B13: CR18008 | C13: 8 | D13: 3.15A, 250V Slow Blow | E13: FUSE | F13: 0 | G13: =4000+400 -> 4400 | I13: =F13+G13-H13 -> 4400 | J13: 2.5 | K13: =I13*J13 -> 11000
J15: TOTAL | K15: =SUM(K6:K12) -> 57250

Sheet CAPACITOR
A2: CAPACITOR STORE STOCK
A4: RAWMATERIAL CODE | B4: CATAGARE NO | C4: SLNO | D4: PART NO | E4: DESCRIPTION | F4: PHY QTY | G4: RECEIPT | H4: ISSUE | I4: BALANCE | J4: UNIT PRICE | K4: AMOUNT
A5: VN0083CP04001 | B5: CP04001 | C5: 1 | D5: B32922C3104K6 | E5: CAPACITOR | I5: =F5+G5-H5 -> 0 | J5: 2.5 | K5: =I5*J5 -> 0
A6: VN0082CP04002 | B6: CP04002 | C6: 2 | D6: 0.1MF-275V.40/100/21 X2 15MM PITCH | E6: CAPACITOR | F6: 41 | I6: =F6+G6-H6 -> 41 | J6: 1 | K6: =I6*J6 -> 41
A7: VN0082CP04003 | B7: CP04003 | C7: 3 | D7: 0.01 MF/250V FFC CAPACITOR FFC | E7: CAPACITOR | F7: 85 | I7: =F7+G7-H7 -> 85 | J7: 1 | K7: =I7*J7 -> 85
A8: VN0083CP04004 | B8: CP04004 | C8: 4 | D8: P2G102K POLY 1KPF /400V | E8: CAPACITOR | F8: 0 | G8: =1000+5000 -> 6000 | H8: 1000 | I8: =F8+G8-H8 -> 5000 | J8: 0.8 | K8: =I8*J8 -> 4000
A9: VN0082CP04005 | B9: CP04005 | C9: 5 | D9: 33PF | E9: CAPACITOR | I9: =F9+G9-H9 -> 0 | J9: 1 | K9: =I9*J9 -> 0
A10: VN0082CP04006 | B10: CP04006 | C10: 6 | D10: CAP POLY BOX 0.22K 275V X2 YELLOW | E10: CAPACITOR(YELLOW) | F10: 125 | I10: =F10+G10-H10 -> 125 | J10: 2 | K10: =I10*J10 -> 250
A11: VN0082CP04007 | B11: CP04007 | C11: 7 | D11: CAPACITOR CERAMIC 103 PF 1KV | E11: DISC CAPACITOR | F11: =11600+202+161 -> 11963 | G11: =6000+40000+6000+4000 -> 56000 | H11: =30+702+1404+3000+15 -> 5151 | I11: =F11+G11-H11 -> 62812 | J11: 0.6 | K11: =I11*J11 -> 37687.2
A12: VN0082CP04008 | B12: CP04008 | C12: 8 | D12: CERAMIC DISC 470 PF / 50V / 20% | E12: DISC CAPACITOR | F12: 100 | I12: =F12+G12-H12 -> 100 | J12: 1 | K12: =I12*J12 -> 100
A13: VN0082CP04009 | B13: CP04009 | C13: 9 | D13: CAP CERAMIC DISC 102 ,1KV | E13: DISC CAPACITOR | F13: =683+90+18+52 -> 843 | I13: =F13+G13-H13 -> 843 | J13: 1 | K13: =I13*J13 -> 843
A14: VN0082CP04011 | B14: CP04010 | C14: 11 | D14: ELE.CAP 100MF/160V / 20% -85@C | E14: ELECTROLYTIC CAPACITOR | F14: 182 | I14: =F14+G14-H14 -> 182 | J14: 3.15 | K14: =I14*J14 -> 573.3
A15: VN0082CP04012 | B15: CP04011 | C15: 12 | D15: ELE.CAP 100uf/250v/ 20% -105@C | E15: ELECTROLYTIC CAPACITOR | F15: 75 | I15: =F15+G15-H15 -> 75 | J15: 3.15 | K15: =I15*J15 -> 236.25
A16: VN0082CP04013 | B16: CP04012 | C16: 13 | D16: ELE.CAP 10mf/250v/ 20% -85@C | E16: ELECTROLYTIC CAPACITOR | F16: 18 | I16: =F16+G16-H16 -> 18 | J16: 3 | K16: =I16*J16 -> 54
A17: VN0082CP04014 | B17: CP04013 | C17: 14 | D17: ELE.CAP 22uf/50v / 20% --105@C | E17: ELECTROLYTIC CAPACITOR | F17: =260+886+6 -> 1152 | G17: =2000+400+5000+16000 -> 23400 | H17: =1+400+1+1+2000+15 -> 2418 | I17: =F17+G17-H17 -> 22134 | J17: 0.55 | K17: =I17*J17 -> 12173.7
A18: VN0082CP04015 | B18: CP04014 | C18: 15 | D18: ELE.CAP 100uf/25v / 20% -105@C | E18: ELECTROLYTIC CAPACITOR | F18: 485 | G18: 5000 | I18: =F18+G18-H18 -> 5485 | J18: 0.78 | K18: =I18*J18 -> 4278.3
A19: VN0082CP04016 | B19: CP04015 | C19: 16 | D19: ELE.CAP 22MFD/400V / 20% --85@C | E19: ELECTROLYTIC CAPACITOR | F19: 5 | I19: =F19+G19-H19 -> 5 | J19: 3 | K19: =I19*J19 -> 15
A20: VN0082CP04017 | B20: CP04016 | C20: 17 | D20: ELE.CAP 22mf/400v / 20% --105@C | E20: ELECTROLYTIC CAPACITOR | F20: 35 | I20: =F20+G20-H20 -> 35 | J20: 3 | K20: =I20*J20 -> 105
A21: VN0082CP04018 | B21: CP04017 | C21: 18 | D21: ELE.CAP 100mf/25v/ 20% | E21: ELECTROLYTIC CAPACITOR | I21: =F21+G21-H21 -> 0 | J21: 3 | K21: =I21*J21 -> 0
A22: VN0082CP04019 | B22: CP04018 | C22: 19 | D22: ELE.CAP 22uf/50v/ 20% | E22: ELECTROLYTIC CAPACITOR | I22: =F22+G22-H22 -> 0 | J22: 3 | K22: =I22*J22 -> 0
A23: VN0082CP04020 | B23: CP04019 | C23: 20 | D23: ELE.CAP 470UF/25V/ 20% | E23: ELECTROLYTIC CAPACITOR | I23: =F23+G23-H23 -> 0 | J23: 4 | K23: =I23*J23 -> 0
A24: VN0082CP04021 | B24: CP04020 | C24: 21 | D24: ELE.CAP 1UF/50V/ 20% --105@C | E24: ELECTROLYTIC CAPACITOR | F24: 0 | G24: =16000+70 -> 16070 | I24: =F24+G24-H24 -> 16070 | J24: 0.78 | K24: =I24*J24 -> 12534.6
A25: VN0082CP04022 | B25: CP04021 | C25: 22 | D25: ELE.CAP 22uF/250V/ 20% --85@C | E25: ELECTROLYTIC CAPACITOR | F25: 49 | G25: 10000 | I25: =F25+G25-H25 -> 10049 | J25: 3.6 | K25: =I25*J25 -> 36176.4
A26: VN0009CP04023 | B26: CP04022 | C26: 23 | D26: 220nF/400V | E26: ELECTROLYTIC CAPACITOR | I26: =F26+G26-H26 -> 0 | J26: 2 | K26: =I26*J26 -> 0
A27: VN0009CP04024 | B27: CP04023 | C27: 24 | D27: 1nF/500V / 1206 | E27: SMD CAPACITERS | F27: 0 | G27: 5000 | I27: =F27+G27-H27 -> 5000 | J27: 1.3 | K27: =I27*J27 -> 6500
A28: VN0009CP04025 | B28: CP04024 | C28: 25 | D28: 470uF/63V / 20% --105@C | E28: ELECTROLYTIC CAPACITOR | F28: 0 | G28: 2500 | I28: =F28+G28-H28 -> 2500 | J28: 4.9 | K28: =I28*J28 -> 12250
A29: VN0009CP04026 | B29: CP04025 | C29: 26 | D29: CAP PLOY 0.047uF/275VAC/ 20% X2 | E29: BOX CAPACITOR | F29: 11 | G29: 5000 | H29: 11 | I29: =F29+G29-H29 -> 5000 | J29: 2.1 | K29: =I29*J29 -> 10500
A30: VN0009CP04027 | B30: CP04026 | C30: 27 | D30: CAP CERAMIC 2.2nF/275VAC/ 20% X1 Y1 | E30: DISC CAPACITOR | F30: 68 | G30: =400+2000+5000+6000+15000 -> 28400 | H30: =10+400+2000 -> 2410 | I30: =F30+G30-H30 -> 26058 | J30: 2.5 | K30: =I30*J30 -> 65145
B31: CP04027 | C31: 28 | D31: CAP POLYESTER 104J 400V | E31: POLY CAPACITOR | F31: 382 | G31: =2000+5000 -> 7000 | H31: =10+372+2000 -> 2382 | I31: =F31+G31-H31 -> 5000 | J31: 1.6 | K31: =I31*J31 -> 8000
B32: CP04028 | C32: 29 | D32: 0.022Mf /275V-X2 | E32: BOX CAPACITOR | G32: =400+2000 -> 2400 | H32: =400+2000 -> 2400 | I32: =F32+G32-H32 -> 0 | J32: 2.25 | K32: =I32*J32 -> 0
B33: CP04029 | C33: 30 | D33: 100nF(104) | F33: 0 | G33: 0 | H33: 0 | I33: 0 | J33: 0 | K33: 0
B34: CP04030 | C34: 31 | D34: 10uF/63V | F34: 0 | G34: 0 | H34: 0 | I34: 0 | J34: 0 | K34: 0
B35: CP04031 | C35: 32 | D35: 100nf/63V | F35: 0 | G35: 0 | H35: 0 | I35: 0 | J35: 0 | K35: 0
B36: CP04032 | C36: 33 | D36: 2.2uF/63V | F36: 0 | G36: 0 | H36: 0 | I36: 0 | J36: 0 | K36: 0
B37: CP04033 | C37: 34 | D37: 47Pf/50V-0805 | E37: CAP_EL_5_3 | F37: 0 | G37: 0 | H37: 0 | I37: 0 | J37: 0 | K37: 0
B38: CP04034 | C38: 35 | D38: 470/50 ELE CAP | E38: CAP_EL_5_4 | F38: 0 | G38: 0 | H38: 0 | I38: 0 | J38: 0 | K38: 0
B39: CP04035 | C39: 36 | D39: 1NF/1000V-0805 | E39: SMD CAPACITERS | F39: 0 | G39: 0 | H39: 0 | I39: 0 | J39: 0 | K39: 0
B40: CP04036 | C40: 37 | D40: 1MF/50V-0805 | E40: SMD CAPACITERS | F40: 0 | G40: 0 | H40: 0 | I40: 0 | J40: 0 | K40: 0
B41: CP04037 | C41: 38 | D41: 470/63 ELE CAP | E41: CAP_EL_5_4 | F41: 0 | G41: 0 | H41: 0 | I41: 0 | J41: 0 | K41: 0
B42: CP04038 | C42: 39 | D42: 10UF/250V | E42: CAP_EL_5_2 | F42: 0 | G42: 0 | H42: 0 | I42: 0 | J42: 0 | K42: 0
B43: CP04039 | C43: 40 | D43: ELE.CAP 470MFD /50 / 20% 85@C | E43: ELECTROLYTIC CAPACITOR | F43: 0 | G43: 0 | H43: 0 | I43: 0 | J43: 0 | K43: 0
B44: CP04040 | C44: 41 | D44: ELE.CAP 22 MFD / 200V / 20% --105@C | E44: ELECTROLYTIC CAPACITOR | F44: 0 | G44: 0 | H44: 0 | I44: 0 | J44: 0 | K44: 0
B45: CP04041 | C45: 42 | D45: ELE.CAP 10 MFD / 200V / 20% --105@C | E45: ELECTROLYTIC CAPACITOR | F45: 0 | G45: 0 | H45: 0 | I45: 0 | J45: 0 | K45: 0
B46: CP04042 | C46: 43 | D46: CAP POLY BOX 0.1MFD /275VAC / 20% X2 10MM PITCH | E46: CAP POLY | F46: 0 | G46: 0 | H46: 0 | I46: 0 | J46: 0 | K46: 0
B47: CP04043 | C47: 44 | D47: CAP POLY 100K / 400V PPC | E47: CAP POLY | F47: 0 | G47: 0 | H47: 0 | I47: 0 | J47: 0 | K47: 0
B48: CP04044 | C48: 45 | D48: CAP POLY 0.1MFD /400V / 20% PPC | E48: CAP POLY | F48: 0 | G48: 0 | H48: 0 | I48: 0 | J48: 0 | K48: 0
... B65: CP04061 | C65: 62 | D65: 680nf/0805/50V | E65: CHIP CAPACITOR | F65: 0 | G65: 0 | H65: 0 | I65: 0 | J65: 0 | K65: 0
B66: CP04062 | C66: 63 | D66: 22nF/275VAC | F66: 0 | G66: 0 | H66: 0 | I66: 0 | J66: 0 | K66: 0
B67: CP04063 | C67: 64 | D67: 100nF 305V AC | E67: X2 BOX CAP (10mm pitch) | F67: 0 | G67: 0 | H67: 0 | I67: 0 | J67: 0 | K67: 0
B68: CP04064 | C68: 65 | D68: SMD CAP 47PF / 50V -1206 | E68: SMD CAPACITOR | F68: 0 | G68: 0 | H68: 0 | I68: 0 | J68: 0 | K68: 0
B69: CP04065 | C69: 66 | D69: 220nf/630V | E69: ELECTROLYTIC CAPACITOR | F69: 0 | G69: 0 | H69: 0 | I69: 0 | J69: 0 | K69: 0
B70: CP04066 | C70: 67 | D70: ELE.CAP 1000 MFD /16V / 20% --105@C | F70: 0 | G70: 0 | H70: 0 | I70: 0 | J70: 0 | K70: 0
B71: CP04067 | C71: 30 | D71: ELE.CAP 1000 MFD /16V / 20% --105@C | E71: ELE.CAP | F71: 9 | I71: =F71+G71-H71 -> 9 | J71: 2.5 | K71: =I71*J71 -> 22.5
B72: CP04068 | C72: 31 | D72: ELE.CAP 4.7mMFD/400v / 20% --105@C | E72: ELECTROLYTIC CAPACITOR | F72: 3 | G72: 5000 | I72: =F72+G72-H72 -> 5003 | J72: 2.7 | K72: =I72*J72 -> 13508.1
B73: CP04069 | C73: 32 | D73: ELE.CAP 22MFD/160V / 20% --85@C | E73: ELECTROLYTIC CAPACITOR | F73: 3 | I73: =F73+G73-H73 -> 3 | J73: 3 | K73: =I73*J73 -> 9
B74: CP04070 | C74: 33 | D74: ELE.CAP 22MFD/63V / 20% --85@C | E74: ELECTROLYTIC CAPACITOR | F74: 12 | I74: =F74+G74-H74 -> 12 | J74: 1 | K74: =I74*J74 -> 12
B75: CP04071 | C75: 34 | D75: ELE.CAP 1MFD/63V / 20% --85@C | E75: ELECTROLYTIC CAPACITOR | F75: 7 | I75: =F75+G75-H75 -> 7 | J75: 1 | K75: =I75*J75 -> 7
B76: CP04072 | C76: 35 | D76: ELE.CAP 470MFD /50 / 20% 85@C | E76: ELECTROLYTIC CAPACITOR | F76: 80 | G76: =400+2000 -> 2400 | H76: =400+2000 -> 2400 | I76: =F76+G76-H76 -> 80 | J76: 4.25 | K76: =I76*J76 -> 340
B77: CP04073 | C77: 36 | D77: ELE.CAP 22 MFD / 200V / 20% --105@C | E77: ELECTROLYTIC CAPACITOR | F77: 24 | I77: =F77+G77-H77 -> 24 | J77: 2.7 | K77: =I77*J77 -> 64.8
B78: CP04074 | C78: 37 | D78: ELE.CAP 10 MFD / 200V / 20% --105@C | E78: ELECTROLYTIC CAPACITOR | F78: 50 | I78: =F78+G78-H78 -> 50 | J78: 4 | K78: =I78*J78 -> 200
B79: CP04075 | C79: 38 | D79: CAP POLY BOX 0.1MFD /275VAC / 20% X2 10MM PITCH | E79: CAP POLY | F79: 31 | G79: =6000+6000 -> 12000 | I79: 1000 | J79: 2.75 | K79: =I79*J79 -> 2750
B80: CP04076 | C80: 39 | D80: CAP POLY 100K / 400V PPC | E80: CAP POLY | F80: 16 | I80: =F80+G80-H80 -> 16 | J80: 3 | K80: =I80*J80 -> 48
B81: CP04077 | C81: 40 | D81: CAP POLY 0.1MFD /400V / 20% PPC | E81: CAP POLY | F81: 26 | I81: =F81+G81-H81 -> 26 | J81: 3.5 | K81: =I81*J81 -> 91
B82: CP04078 | C82: 41 | D82: ELE.CAP 2.2MFD /450V / 20% --85@C | E82: ELECTROLYTIC CAPACITOR | F82: 39 | I82: =F82+G82-H82 -> 39 | J82: 8 | K82: =I82*J82 -> 312
B83: CP04079 | C83: 42 | D83: ELE.CAP 10MFD/250V/ 20% -105@C | E83: ELECTROLYTIC CAPACITOR | F83: =40+39+40+30+130+4 -> 283 | I83: =F83+G83-H83 -> 283 | J83: 4.5 | K83: =I83*J83 -> 1273.5
B84: CP04080 | C84: 43 | D84: ELE.CAP 10MFD/200V/ 20% -105@C | E84: ELECTROLYTIC CAPACITOR | F84: 50 | I84: =F84+G84-H84 -> 50 | J84: 4.5 | K84: =I84*J84 -> 225
B85: CP04081 | C85: 44 | D85: CAP POLY 224J /400V /20% | E85: CAP POLY | F85: 483 | I85: =F85+G85-H85 -> 483 | J85: 4 | K85: =I85*J85 -> 1932
B86: CP04082 | C86: 45 | D86: ELE.CAP 22MFD/250V/ 20% -105@C | E86: ELECTROLYTIC CAPACITOR | F86: 8782 | H86: =20+1404+600+2000+10 -> 4034 | I86: =F86+G86-H86 -> 4748 | J86: 3.5 | K86: =I86*J86 -> 16618
B87: CP04083 | C87: 46 | D87: CAP.POLY 224 /630V / 20% | E87: CAP POLY | F87: =3310+500 -> 3810 | H87: =10+702+5+15 -> 732 | I87: =F87+G87-H87 -> 3078 | J87: 2.5 | K87: =I87*J87 -> 7695
B88: CP04084 | C88: 47 | D88: CAP POLY 22NF/300V / 20% X2 10MM PITCH | E88: CAP POLY | F88: 120 | G88: 6000 | I88: =F88+G88-H88 -> 6120 | J88: 2.25 | K88: =I88*J88 -> 13770
B89: CP04085 | C89: 48 | D89: ELE.CAP 100 MFD /35V / 20% --105@C | E89: ELECTROLYTIC CAPACITOR | F89: 7 | I89: =F89+G89-H89 -> 7 | J89: 2.5 | K89: =I89*J89 -> 17.5
B90: CP04086 | C90: 49 | D90: ELE.CAP 470UF/50V/ 20%--85@C | E90: ELECTROLYTIC CAPACITOR | F90: 8 | H90: 1 | I90: =F90+G90-H90 -> 7 | J90: 2.9 | K90: =I90*J90 -> 20.3
B91: CP04087 | C91: 50 | D91: ELE.CAP 10MFD/450V/ 20% -105@C | E91: ELECTROLYTIC CAPACITOR | F91: 1 | I91: =F91+G91-H91 -> 1 | J91: 4.5 | K91: =I91*J91 -> 4.5
B92: CP04088 | C92: 51 | D92: ELE.CAP 2.2MFD/450V/ 20% -105@C | E92: ELECTROLYTIC CAPACITOR | F92: 5 | I92: =F92+G92-H92 -> 5 | J92: 8 | K92: =I92*J92 -> 40
B93: CP04089 | C93: 52 | D93: ELE.CAP 47MFD/200V/ 20% -105@C | E93: ELECTROLYTIC CAPACITOR | F93: 6 | I93: =F93+G93-H93 -> 6 | J93: 6 | K93: =I93*J93 -> 36
B94: CP04090 | C94: 53 | D94: ELE.CAP 100MFD/100V/ 20% -105@C | E94: ELECTROLYTIC CAPACITOR | F94: 2 | I94: =F94+G94-H94 -> 2 | J94: 4.5 | K94: =I94*J94 -> 9
B95: CP04091 | C95: 54 | D95: ELE.CAP 220MFD/100V/ 20% -105@C | E95: ELECTROLYTIC CAPACITOR | F95: 0 | G95: 2500 | I95: =F95+G95-H95 -> 2500 | J95: 3.75 | K95: =I95*J95 -> 9375
B96: CP04092 | C96: 55 | D96: CAP POLY 47NF/275V / 20% X2 10MM PITCH | E96: CAP POLY | F96: 0 | G96: =4000+10000 -> 14000 | I96: =F96+G96-H96 -> 14000 | J96: 2.75 | K96: =I96*J96 -> 38500
B97: CP04093 | D97: ELE.CAP 470UF/50V/ 20%--105@C | E97: ELECTROLYTIC CAPACITOR | F97: 0 | G97: 5000 | I97: 5000 | J97: 4.55 | K97: =I97*J97 -> 22750
B98: CP04094 | D98: ELE.CAP 220UF/50V/ 20%--105@C | E98: ELECTROLYTIC CAPACITOR | F98: 0 | G98: 5000 | I98: 5000 | J98: 2.85 | K98: =I98*J98 -> 14250
B99: CP04095 | D99: ELE.CAP 220UF/63V/ 20%--105@C | E99: ELECTROLYTIC CAPACITOR | F99: 0 | G99: 5000 | I99: 5000 | J99: 3.25 | K99: =I99*J99 -> 16250
B100: CP04096 | D100: 1UF/50V/0805 | E100: CHIP RESISTOR | I100: 5000 | J100: 0.35 | K100: =I100*J100 -> 1750
J101: TOTAL AMOUNT | K101: =SUM(K5:K100) -> 373427.95

Sheet HEATSINK
A3: HEAT SINK STORE STOCK
A5: RAWMATERIAL CODE | B5: CATAGARE NO | C5: SLNO | D5: PART NO | E5: DESCRIPTION | F5: PHY QTY | G5: RECEIPT | H5: ISSUE | I5: BALANCE | J5: UNIT PRICE | K5: AMOUNT
A6: VN0009HS03001 | B6: HS03001 | C6: 1 | D6: HEAT SINK STRIP | E6: HEAT SINK | F6: 0 | I6: =F6+G6-H6 -> 0 | J6: 10 | K6: =I6*J6 -> 0
A7: VN0009HS03002 | B7: HS03002 | C7: 2 | D7: HEAT SINK COMPOND | E7: HEAT SINK COMPOND | F7: 0 | I7: =F7+G7-H7 -> 0 | J7: 30 | K7: =I7*J7 -> 0
A8: VN0009HS03003 | B8: HS03003 | C8: 3 | D8: HS-501 | E8: HEAT SINK | F8: 0 | I8: =F8+G8-H8 -> 0 | J8: 0 | K8: =I8*J8 -> 0
C9: 4 | D9: HEAT SINK U TYPE | E9: HEAT SINK | F9: 0 | G9: =10+32 -> 42 | I9: =F9+G9-H9 -> 42 | J9: 5 | K9: =I9*J9 -> 210
C10: 5
J11: TOTAL | K11: =SUM(K6:K10) -> 210

Sheet INDUCTOR
A3: INDUCTORE STORE STOCK
A5: RAWMATERIAL CODE | B5: CATAGARE NO | C5: SLNO | D5: PART NO | E5: DESCRIPTION | F5: PHY QTY | G5: RECEIPT | H5: ISSUE | I5: BALANCE | J5: UNIT PRICE | K5: AMOUNT
A6: VN0080IN08001 | B6: IN08001 | C6: 1 | D6: 3.3MH | E6: INDUCTOR | I6: =F6+G6-H6 -> 0 | J6: 1.32 | K6: =I6*J6 -> 0
A7: VN0043IN08002 | B7: IN08002 | C7: 2 | D7: 1mH AL 0510 | E7: INDUCTOR | F7: 11000 | H7: =20+20+800+2806+20+50+5+15+1000+4000+15 -> 8751 | I7: =F7+G7-H7 -> 2249 | J7: 0.91 | K7: =I7*J7 -> 2046.59
A8: VN0063IN08003 | B8: IN08003 | C8: 3 | D8: EE-16 INDUCTOR | E8: INDUCTOR | F8: =520+150 -> 670 | H8: =400+161 -> 561 | I8: =F8+G8-H8 -> 109 | J8: 7.5 | K8: =I8*J8 -> 817.5
A9: VN0080IN08004 | B9: IN08004 | C9: 4 | D9: 1 Mh | E9: INDUCTOR | I9: =F9+G9-H9 -> 0 | J9: 2.75 | K9: =I9*J9 -> 0
A10: VN0043IN08003 | B10: IN08005 | C10: 5 | D10: 2.2 Mh/300mA 10 X 12WL | E10: INDUCTOR | I10: =F10+G10-H10 -> 0 | J10: 7.5 | K10: =I10*J10 -> 0
A11: VN0063IN08004 | B11: IN08006 | C11: 6 | D11: 42v/240mA | E11: Transformer | I11: =F11+G11-H11 -> 0 | J11: 25 | K11: =I11*J11 -> 0
A12: VN0080IN08005 | B12: IN08007 | C12: 7 | D12: EE-16 TRNS 24/350 MA | E12: Transformer | F12: 140 | I12: =F12+G12-H12 -> 140 | J12: 12 | K12: =I12*J12 -> 1680
A13: VN0043IN08004 | B13: IN08008 | C13: 8 | D13: EE-20 TRNS 42/360 10PIN ( MT11448 ) | E13: Transformer | F13: 0 | G13: =1560+2000 -> 3560 | I13: =F13+G13-H13 -> 3560 | J13: 16 | K13: =I13*J13 -> 56960
B14: IN08009 | C14: 9 | D14: EE-16 TRNS 24V/360MA | E14: Transformer | F14: 360 | I14: =F14+G14-H14 -> 360 | J14: 12 | K14: =I14*J14 -> 4320
B15: IN08010 | C15: 10 | D15: EE-16 TRANS 5W-DL 2.0 | E15: Transformer | F15: 650 | I15: =F15+G15-H15 -> 650 | J15: 10 | K15: =I15*J15 -> 6500
B16: IN08011 | C16: 11 | D16: EE-16 MT 1584 | E16: Transformer | F16: =81+81 -> 162 | I16: =F16+G16-H16 -> 162 | J16: 10 | K16: =I16*J16 -> 1620
B17: IN08012 | C17: 12 | D17: INDUCTOR 0.65Mh | E17: INDUCTOR | F17: 10 | I17: =F17+G17-H17 -> 10 | J17: 20 | K17: =I17*J17 -> 200
B18: IN08013 | C18: 13 | D18: INDUCTOR 0.68Mh | E18: INDUCTOR | F18: 5 | I18: =F18+G18-H18 -> 5 | J18: 20 | K18: =I18*J18 -> 100
B19: IN08014 | C19: 14 | D19: INDUCTOR 2.4mH --EE16 | E19: INDUCTOR | G19: 1443 | H19: =1400 -> 1400 | I19: =F19+G19-H19 -> 43 | J19: 7.5 | K19: =I19*J19 -> 322.5
B20: IN08015 | C20: 15 | D20: TRANSFORMER EE16-24V/350MA -MT15942 | E20: Transformer | F20: 0 | G20: =500+500 -> 1000 | H20: =500+6 -> 506 | I20: =F20+G20-H20 -> 494 | J20: 12 | K20: =I20*J20 -> 5928
B21: IN08017 | C21: 16 | D21: TRANSFORMER EE13 --ETR | E21: Transformer | F21: 0 | G21: =1000+1000 -> 2000 | I21: =F21+G21-H21 -> 2000 | J21: 9 | K21: =I21*J21 -> 18000
B22: IN08016 | C22: 17 | D22: EE16-4.5MH | E22: Transformer
B23: IN08017 | C23: 18 | D23: EE13 | E23: Transformer
B24: IN08018 | C24: 19 | D24: SK1.25MH | E24: Transformer
B25: IN08019 | C25: 20 | D25: 2.2mH | E25: Transformer
B26: IN08020 | C26: 21 | D26: EE25 H | E26: Transformer
B27: IN08021 | C27: 22 | D27: ETR-EE13 HORIZONTAL 2.2~2.3mH TRANSFORMER | E27: Transformer
B28: IN08022 | C28: 23 | D28: INDUCTOR 1MH / 300mA size 8x10 | E28: inductor | F28: 0 | G28: =1000+2000+4500 -> 7500 | I28: =F28+G28-H28 -> 7500 | J28: 5 | K28: 5000
B29: IN08023 | C29: 24 | D29: EE-25 TRANSFORMER MT 4512 | E29: Transformer
B30: IN08024 | C30: 25 | D30: 2.4MH /0.7A/ 12 X 15 | E30: INDUCTOR
B31: IN08025 | C31: 26 | D31: EF20 H MT- 10031 | E31: Transformer
C32: 27 | D32: INDUCTOR 3mH -EE16 | E32: INDUCTOR | G32: 1050 | I32: =F32+G32-H32 -> 1050 | J32: 7.5 | K32: =I32*J32 -> 7875
C33: 28 | D33: TRANSFORMER EE16-24V/350MA -MT15942 | H33: =E33+F33-G33 -> 0 | I33: =F33+G33-H33 -> 0 | J33: 2.75
C34: 29 | D34: EE20 - TRANSFORMER 10031 | E34: Transformer | G34: =1000+1000 -> 2000 | I34: =F34+G34-H34 -> 2000 | J34: 16 | K34: =I34*J34 -> 32000
C35: 30 | D35: EE16 - TRANSFORMER 15947 | E35: Transformer | F35: 0 | G35: 2000 | I35: =F35+G35-H35 -> 2000 | J35: 12 | K35: =I35*J35 -> 24000
J36: TOTAL | K36: =SUM(K6:K28) -> 103494.59

Sheet MOSFET
A4: MOSFET STORE STOCK
A6: RAWMATERIAL CODE | B6: CATAGARE NO | C6: SLNO | D6: PART NO | E6: DESCRIPTION | F6: PHY QTY | G6: RECEIPT | H6: ISSUE | I6: BALANCE | J6: UNIT PRICE | K6: AMOUNT | L6: As per physical count
A7: SM0105MF02001 | B7: MF02001 | C7: 1 | D7: SMUA2121 A 207 1P | E7: MOSFET | I7: =F7+G7-H7 -> 0 | J7: 15 | K7: =I7*J7 -> 0
A8: SM0105MF02002 | B8: MF02002 | C8: 2 | D8: 5N50 | E8: MOSFET | I8: =F8+G8-H8 -> 0 | J8: 17.4 | K8: =I8*J8 -> 0
A9: SM0105MF02003 | B9: MF02003 | C9: 3 | D9: MSU2NGO | E9: MOSFET | I9: =F9+G9-H9 -> 0 | J9: 5.52 | K9: =I9*J9 -> 0
A10: SM0105MF02004 | B10: MF02004 | C10: 4 | D10: SM4N60 | E10: MOSFET | F10: 2409 | G10: =250+5000+6973+4000+23000 -> 39223 | H10: =10+12+702+65+1000+8+5 -> 1802 | I10: =F10+G10-H10 -> 39830 | J10: 11.15 | K10: =I10*J10 -> 444104.5
A11: SM0105MF02005 | B11: MF02005 | C11: 5 | D11: SMN-2N60 | E11: MOSFET | F11: =36000+96+30+131+1875+1950 -> 40082 | H11: =400+2000 -> 2400 | I11: =F11+G11-H11 -> 37682 | J11: 12 | K11: =I11*J11 -> 452184 | L11: 37725
A12: VN0009MF02006 | B12: MF02006 | C12: 6 | D12: 10N80-FSC | E12: MOSFET | I12: =F12+G12-H12 -> 0 | J12: 28 | K12: =I12*J12 -> 0
B13: MF02007 | C13: 7 | D13: IRFZ44N | E13: MOSFET | I13: =F13+G13-H13 -> 0 | K13: =I13*J13 -> 0
B14: MF02008 | C14: 8 | D14: 12N90 | E14: MOSFET
B15: MF02009 | C15: 9 | D15: 4N80T.TO-220 | E15: MOSFET
B16: MF02010 | C16: 8 | D16: 4N60C | E16: MOSFET | F16: 9 | H16: 7 | I16: =F16+G16-H16 -> 2 | J16: 38 | K16: =I16*J16 -> 76
J17: TOTAL | K17: =SUM(K7:K15) -> 896288.5

Sheet DRIVER
D1: SEMTRONICS MICROSYSTEMS PVT LTD
D2: G.G STOCK AS ON 31.12.2013
A3: DRIVER STORE STOCK
J4: 13.01.2014
A5: RAWMATERIAL CODE | B5: CATAGARE NO | C5: SLNO | D5: PART NO | E5: DESCRIPTION | F5: PHY QTY | G5: 31.12.13 | H5: RECEIPT | I5: ISSUE | J5: BALANCE | K5: UNIT PRICE | L5: AMOUNT
A6: SM0105DR13001 | B6: DR13001 | C6: 1 | D6: E27-SEM V1 | E6: DRIVER | F6: 188 | G6: 188 | J6: =G6+H6-I6 -> 188 | K6: 80 | L6: =J6*K6 -> 15040
A7: SM0105DR13002 | B7: DR13002 | C7: 2 | D7: 3 WATT DC DC | E7: DRIVER | F7: 0 | J7: =G7+H7-I7 -> 0 | K7: 70 | L7: =J7*K7 -> 0
A8: SM0105DR13003 | B8: DR13003 | C8: 3 | D8: ISOLATED DOWN LIGHT DRIVER | E8: DRIVER | F8: 0 | J8: =G8+H8-I8 -> 0 | K8: 180 | L8: =J8*K8 -> 0
A9: SM0105DR13004 | B9: DR13004 | C9: 4 | D9: T8 -18 Watt ISOLATED TUBE LIGHT DRIVER | E9: DRIVER | F9: 1450 | G9: 1450 | J9: =G9+H9-I9 -> 1450 | K9: 105 | L9: =J9*K9 -> 152250
A10: SM0105DR13005 | B10: DR13005 | C10: 5 | D10: T8 -24 Watt ISOLATED TUBE LIGHT DRIVER | E10: DRIVER | F10: 932 | G10: 730 | I10: 100 | J10: =G10+H10-I10 -> 630 | K10: 110 | L10: =J10*K10 -> 69300
A11: SM0105DR13006 | B11: DR13006 | C11: 6 | D11: 20 WATT AC DC LED DRIVER | E11: DRIVER | F11: 0 | J11: =G11+H11-I11 -> 0 | K11: 300 | L11: =J11*K11 -> 0
A12: SM0105DR13007 | B12: DR13007 | C12: 7 | D12: 8-12 WATT 350mA DRIVER | E12: DRIVER | F12: 0 | J12: =G12+H12-I12 -> 0 | K12: 60 | L12: =J12*K12 -> 0
A13: SM0105DR13008 | B13: DR13008 | C13: 8 | D13: 10-15 WATT 700mA DRIVER | E13: DRIVER | F13: 0 | J13: =G13+H13-I13 -> 0 | K13: 300 | L13: =J13*K13 -> 0
A14: SM0105DR13009 | B14: DR13009 | C14: 9 | D14: 15-20 WATT 350mA DRIVER B | E14: DRIVER | F14: 102 | G14: 112 | J14: =G14+H14-I14 -> 112 | K14: 60 | L14: =J14*K14 -> 6720
A15: SM0105DR13010 | B15: DR13010 | C15: 10 | D15: 12-18WATT 350mA DRIVER | E15: DRIVER | F15: 0 | G15: 193 | J15: =G15+H15-I15 -> 193 | K15: 300 | L15: =J15*K15 -> 57900
A16: SM0105DR13011 | B16: DR13011 | C16: 11 | D16: 1-3 WATT 350mA DRIVER | E16: DRIVER | F16: 5030 | G16: 3846 | I16: =6+100+5+1+2+10+20 -> 144 | J16: 0 | K16: 55 | L16: =J16*K16 -> 0
A17: SM0105DR13012 | B17: DR13012 | C17: 12 | D17: 7-12WATT 350mA DRIVER A | E17: DRIVER | F17: 5 | G17: 680 | I17: 0 | J17: 0 | K17: 114 | L17: =J17*K17 -> 0
A18: SM0105DR13013 | B18: DR13013 | C18: 13 | D18: 4-7 WATT 350mA DRIVER A | E18: DRIVER | F18: 3 | H18: 50 | I18: 50 | J18: =G18+H18-I18 -> 0 | K18: 74 | L18: =J18*K18 -> 0
A19: SM0105DR13014 | B19: DR13014 | C19: 14 | D19: 30-35 WATT 600mA DRIVER | E19: DRIVER | F19: 0 | G19: 13 | J19: =G19+H19-I19 -> 13 | K19: 445 | L19: =J19*K19 -> 5785
A20: SM0105DR13015 | B20: DR13015 | C20: 15 | D20: 12-18WATT 700mA DRIVER | E20: DRIVER | F20: 0 | J20: =G20+H20-I20 -> 0 | K20: 300 | L20: =J20*K20 -> 0
A21: SM0105DR13016 | B21: DR13016 | C21: 16 | D21: 2-8 watt 350mA DRIVER | E21: DRIVER | F21: 0 | J21: =G21+H21-I21 -> 0 | K21: 55 | L21: =J21*K21 -> 0
A22: SM0105DR13017 | B22: DR13017 | C22: 17 | D22: 20-25WATT 350mA DRIVER | E22: DRIVER | F22: 0 | G22: 139 | J22: =G22+H22-I22 -> 139 | K22: 350 | L22: =J22*K22 -> 48650
A23: SM0105DR13018 | B23: DR13018 | C23: 18 | D23: E27 4.5 VER | E23: DRIVER | F23: 1900 | G23: 299 | J23: 0 | K23: 128 | L23: =J23*K23 -> 0
A24: SM0105DR13019 | B24: DR13019 | C24: 19 | D24: T8 TUBE LIGHT DRIVER 4.5 VER | E24: DRIVER | F24: 200 | J24: 150 | K24: 105 | L24: =J24*K24 -> 15750
A25: SM0105DR13020 | B25: DR13020 | C25: 20 | D25: T8 TUBE LIGHT DRIVER 4.2 VER | E25: DRIVER | F25: 15 | G25: 190 | J25: =G25+H25-I25 -> 190 | K25: 90 | L25: =J25*K25 -> 17100
A26: SM0105DR13021 | B26: DR13021 | C26: 21 | D26: T8 TUBE LIGHT DRIVER 5.4 VER | E26: DRIVER | F26: 56 | H26: =100+50+182 -> 332 | I26: =100+50+100 -> 250 | J26: 0 | K26: 105 | L26: =J26*K26 -> 0
A27: SM0105DR13022 | B27: DR13022 | C27: 22 | D27: 6 WATT DC DC | E27: DRIVER | F27: 23 | J27: =G27+H27-I27 -> 0 | K27: 75 | L27: =J27*K27 -> 0
A28: SM0105DR13023 | B28: DR13023 | C28: 23 | D28: E27-SEM 6W | E28: DRIVER | F28: 59 | J28: =G28+H28-I28 -> 0 | K28: 80 | L28: =J28*K28 -> 0
A29: SM0105DR13024 | B29: DR13024 | C29: 24 | D29: E27-SEM 8W | E29: DRIVER | F29: 140 | J29: =G29+H29-I29 -> 0 | K29: 80 | L29: =J29*K29 -> 0
A30: SM0105DR13025 | B30: DR13025 | C30: 25 | D30: E27-SEM 2W | E30: DRIVER | F30: 100 | J30: =G30+H30-I30 -> 0 | K30: 75 | L30: =J30*K30 -> 0
A31: SM0105DR13026 | B31: DR13026 | C31: 26 | D31: E27-CS-EM1 MISSING COMPONENTS | E31: DRIVER | F31: 150 | J31: =G31+H31-I31 -> 0 | K31: 35 | L31: =J31*K31 -> 0
A32: SM0105DR13027 | B32: DR13027 | C32: 27 | D32: TUBE LIGHT 4.4 VER | E32: DRIVER | F32: 0 | J32: =G32+H32-I32 -> 0 | K32: 105 | L32: =J32*K32 -> 0
A33: SM0105DR13028 | B33: DR13028 | C33: 28 | D33: 4-7 WATT 350mA DRIVER B | E33: DRIVER | F33: 1406 | G33: 1312 | I33: 175 | J33: 0 | K33: 74 | L33: =J33*K33 -> 0
A34: SM0105DR13029 | B34: DR13029 | C34: 29 | D34: 20-25WATT 700mA DRIVER | E34: DRIVER | F34: 0 | J34: =G34+H34-I34 -> 0 | K34: 350 | L34: =J34*K34 -> 0
A35: SM0105DR13030 | B35: DR13030 | C35: 30 | D35: 1-3 WATT 1mA DRIVER | E35: DRIVER | F35: 26 | G35: 23 | J35: =G35+H35-I35 -> 23 | K35: 55 | L35: =J35*K35 -> 1265
A36: SM0105DR13031 | B36: DR13031 | C36: 31 | D36: 2-6 watt 350mA DRIVER | E36: DRIVER | F36: 60 | G36: 63 | J36: =G36+H36-I36 -> 63 | K36: 55 | L36: =J36*K36 -> 3465
A37: SM0105DR13032 | B37: DR13032 | C37: 32 | D37: 1-3 WATT 700mA DRIVER | E37: DRIVER | F37: 0 | J37: =G37+H37-I37 -> 0 | K37: 55 | L37: =J37*K37 -> 0
A38: SM0105DR13033 | B38: DR13033 | C38: 33 | D38: 7-12WATT 300mA DRIVER B | E38: DRIVER | F38: 152 | G38: 191 | J38: 0 | K38: 114 | L38: =J38*K38 -> 0
A39: SM0105DR13034 | B39: DR13034 | C39: 34 | D39: 8-10 WATT 150mA DRIVER | E39: DRIVER | F39: 0 | J39: =G39+H39-I39 -> 0 | K39: 55 | L39: =J39*K39 -> 0
A40: SM0105DR13035 | B40: DR13035 | C40: 35 | D40: 40-45 WATT 1.05mA DRIVER | E40: DRIVER | F40: 1 | J40: =G40+H40-I40 -> 0 | K40: 145 | L40: =J40*K40 -> 0
A41: SM0105DR13036 | B41: DR13036 | C41: 36 | D41: 72 WATT CIRCULER DRIVER | E41: DRIVER | F41: 120 | J41: =G41+H41-I41 -> 0 | K41: 250 | L41: =J41*K41 -> 0
A42: SM0105DR13037 | B42: DR13037 | C42: 37 | D42: 12-18WATT 350mA DRIVER | E42: DRIVER | F42: 0 | G42: 310 | J42: =G42+H42-I42 -> 310 | K42: 300 | L42: =J42*K42 -> 93000
A43: SM0105DR13038 | B43: DR13038 | C43: 38 | D43: 4-7 WATT 320mA DRIVER (SM6300B) | E43: DRIVER | F43: 0 | J43: =G43+H43-I43 -> 0 | K43: 0 | L43: =J43*K43 -> 0
A44: SM0105DR13039 | B44: DR13039 | C44: 39 | D44: 10-15 WATT 300mA DRIVER (SM6300B) | E44: DRIVER | F44: 0 | J44: =G44+H44-I44 -> 0 | K44: 110 | L44: =J44*K44 -> 0
A45: SM0105DR13040 | B45: DR13040 | C45: 40 | D45: 1-3 WATT 350mA DRIVER B | E45: DRIVER | F45: 40 | J45: =G45+H45-I45 -> 0 | K45: 55 | L45: =J45*K45 -> 0
A46: SM0105DR13041 | B46: DR13041 | C46: 41 | D46: 45WATT 700MA PFC+5V600MA B | E46: DRIVER | F46: 39 | J46: =G46+H46-I46 -> 0 | K46: 122 | L46: =J46*K46 -> 0
A47: SM0105DR13042 | B47: DR13042 | C47: 42 | D47: 3W 300MA DC-DC | E47: DRIVER | F47: 494 | J47: =G47+H47-I47 -> 0 | K47: 50 | L47: =J47*K47 -> 0
A48: SM0105DR13043 | B48: DR13043 | C48: 43 | D48: 5W 300MA DC-DC | E48: DRIVER | F48: 500 | J48: =G48+H48-I48 -> 0 | K48: 60 | L48: =J48*K48 -> 0
A49: SM0105DR13044 | B49: DR13044 | C49: 44 | D49: 7-12WATT 350mA DRIVER B | E49: DRIVER | F49: 736 | G49: 879 | J49: 0 | K49: 114 | L49: =J49*K49 -> 0
A50: SM0105DR13045 | B50: DR13045 | C50: 45 | D50: 10W230MA 40V DC-DC | E50: DRIVER | F50: 30 | J50: =G50+H50-I50 -> 0 | K50: 70 | L50: =J50*K50 -> 0
A51: SM0105DR13046 | B51: DR13046 | C51: 46 | D51: 4-7W 300MA PFC SM6300B | E51: DRIVER | F51: 5930 | G51: 5873 | I51: =10+4 -> 14 | J51: 0 | K51: 74 | L51: =J51*K51 -> 0
A52: SM0105DR13047 | B52: DR13047 | C52: 47 | D52: 7-12W 300MA PFC SM6300B | E52: DRIVER | F52: 0 | J52: =G52+H52-I52 -> 0 | K52: 0 | L52: =J52*K52 -> 0
A53: SM0105DR13048 | B53: DR13048 | C53: 48 | D53: 12-18W 300MA PFC SM6300B | E53: DRIVER | F53: 0 | J53: =G53+H53-I53 -> 0 | K53: 0 | L53: =J53*K53 -> 0
A54: SM0105DR13049 | B54: DR13049 | C54: 49 | D54: 4-5W 38V-42V 120MA SM6300B | E54: DRIVER | F54: 0 | J54: =G54+H54-I54 -> 0 | K54: 60 | L54: =J54*K54 -> 0
A55: SM0105DR13050 | B55: DR13050 | C55: 50 | D55: 9-10W 38V-42V 240MA SM6300B | E55: DRIVER | F55: 0 | J55: =G55+H55-I55 -> 0 | K55: 0 | L55: =J55*K55 -> 0
A56: SM0105DR13051 | B56: DR13051 | C56: 51 | D56: 13-15W 38V-42V 360MA SM6300B | E56: DRIVER | F56: 0 | J56: =G56+H56-I56 -> 0 | K56: 0 | L56: =J56*K56 -> 0
A57: SM0105DR13052 | B57: DR13052 | C57: 52 | D57: 32W 1.28A | E57: DRIVER | F57: 0 | J57: =G57+H57-I57 -> 0 | K57: 0 | L57: =J57*K57 -> 0
A58: SM0105DR13053 | B58: DR13053 | C58: 53 | D58: 6W 700MA Class A | E58: DRIVER | F58: 0 | J58: =G58+H58-I58 -> 0 | K58: 0 | L58: =J58*K58 -> 0
A59: SM0105DR13054 | B59: DR13054 | C59: 54 | D59: 5-12 WATT SM6300B | E59: DRIVER | F59: 0 | G59: 416 | J59: =G59+H59-I59 -> 416 | K59: 0 | L59: =J59*K59 -> 0
A60: SM0105DR13055 | B60: DR13055 | C60: 55 | D60: 2-6 WATT150mA B | E60: DRIVER | F60: 8 | J60: =G60+H60-I60 -> 0 | K60: 50 | L60: =J60*K60 -> 0
A61: SM0105DR13056 | B61: DR13056 | C61: 56 | D61: 4-8 WATT 320 Ma | E61: DRIVER | F61: 0 | J61: =G61+H61-I61 -> 0 | K61: 60 | L61: =J61*K61 -> 0
A62: SM0105DR13057 | B62: DR13057 | C62: 57 | D62: 4-7 watt 300mA( A) | E62: DRIVER | F62: 380 | G62: 138 | J62: =G62+H62-I62 -> 138 | K62: 60 | L62: =J62*K62 -> 8280
A63: SM0105DR13058 | B63: DR13058 | C63: 58 | D63: 45 WATT 1.2A | E63: DRIVER | F63: 0 | G63: 20 | J63: =G63+H63-I63 -> 20 | K63: 0 | L63: =J63*K63 -> 0
A64: SM0105DR13059 | B64: DR13059 | C64: 59 | D64: 27V 1.2A (32 WATT) | E64: DRIVER | F64: 20 | G64: 18 | J64: =G64+H64-I64 -> 18 | K64: 0 | L64: =J64*K64 -> 0
A65: SM0105DR13060 | B65: DR13060 | C65: 60 | D65: T8 TUBE LIGHT DRIVER 5.8 VER | E65: DRIVER | F65: =7000-25 -> 6975 | G65: 1137 | J65: =G65+H65-I65 -> 1137 | K65: 110 | L65: =J65*K65 -> 125070
A66: SM0105DR13061 | B66: DR13061 | C66: 61 | D66: SEM SURGE VER1.0 | E66: DRIVER | F66: 4000 | G66: 7420 | H66: 608 | J66: =G66+H66-I66 -> 8028 | K66: 20 | L66: =J66*K66 -> 160560
A67: SM0105DR13062 | B67: DR13062 | C67: 62 | D67: EE 18-36 WATT 700mA | E67: DRIVER | F67: 100 | G67: 165 | J67: =G67+H67-I67 -> 165 | K67: 120 | L67: =J67*K67 -> 19800
A68: SM0105DR13063 | B68: DR13063 | C68: 63 | D68: 30-35 WATT 700mA DRIVER(BLUE COLOUR) | E68: DRIVER | F68: 50 | J68: =G68+H68-I68 -> 0 | K68: 170 | L68: =J68*K68 -> 0
A69: SM0105DR13064 | B69: DR13064 | C69: 64 | D69: 18-24 watt 350mA | E69: DRIVER | F69: 10 | G69: 249 | J69: =G69+H69-I69 -> 249 | K69: 150 | L69: =J69*K69 -> 37350
A70: SM0105DR13065 | B70: DR13065 | C70: 65 | D70: 24-36 Watt 410mA | E70: DRIVER | F70: 10 | G70: 25 | J70: =G70+H70-I70 -> 25 | K70: 150 | L70: =J70*K70 -> 3750
A71: SM0105DR13066 | B71: DR13066 | C71: 66 | D71: 24-42 Watt 240mA | E71: DRIVER | F71: 10 | G71: 198 | J71: =G71+H71-I71 -> 198 | K71: 170 | L71: =J71*K71 -> 33660
A72: SM0105DR13067 | B72: DR13067 | C72: 67 | D72: 18-36Watt 600mA | E72: DRIVER | F72: 10 | G72: 167 | J72: =G72+H72-I72 -> 167 | K72: 160 | L72: =J72*K72 -> 26720
A73: SM0105DR13068 | B73: DR13068 | C73: 68 | D73: 5 WATT (6300B VER1.4) DRIVER | E73: DRIVER | F73: 150 | J73: =G73+H73-I73 -> 0 | K73: 120 | L73: =J73*K73 -> 0
A74: SM0105DR13069 | B74: DR13069 | C74: 69 | D74: 10 WATT (6300B VER1.4) DRIVER | E74: DRIVER | F74: 150 | J74: =G74+H74-I74 -> 0 | K74: 120 | L74: =J74*K74 -> 0
A75: SM0105DR13070 | B75: DR13070 | C75: 70 | D75: 15 WATT (6300B VER1.4) DRIVER | E75: DRIVER | F75: 150 | J75: =G75+H75-I75 -> 0 | K75: 120 | L75: =J75*K75 -> 0
A76: SM0105DR13071 | B76: DR13071 | C76: 71 | D76: 5-10 WATT SM6300B | E76: DRIVER | F76: 150 | H76: 400 | I76: 100 | J76: 0 | K76: 110 | L76: =J76*K76 -> 0
A77: SM0105DR13072 | B77: DR13072 | C77: 72 | D77: 24-42 Watt 120mA,A | E77: DRIVER | F77: 90 | G77: 90 | J77: =G77+H77-I77 -> 90 | K77: 110 | L77: =J77*K77 -> 9900
A78: SM0105DR13073 | B78: DR13073 | C78: 73 | D78: 10-20 W DC DC | E78: DRIVER | F78: 197 | G78: 175 | J78: 90 | K78: 90 | L78: =J78*K78 -> 8100
A79: SM0105DR13074 | B79: DR13074 | C79: 74 | D79: 20-30 WATT DC DC | E79: DRIVER | F79: 18 | J79: =G79+H79-I79 -> 0 | K79: 110 | L79: =J79*K79 -> 0
A80: SM0105DR13075 | B80: DR13075 | C80: 75 | D80: 30-35 W 25V 1.32A SM6300B | E80: DRIVER | G80: 20 | J80: =G80+H80-I80 -> 20 | K80: 160 | L80: =J80*K80 -> 3200
A81: SM0105DR13076 | B81: DR13076 | C81: 76 | D81: 4-7 WATT 700mA CLASS B | E81: DRIVER | J81: =G81+H81-I81 -> 0 | K81: 60 | L81: =J81*K81 -> 0
A82: SM0105DR13077 | B82: DR13077 | C82: 77 | D82: SM3300 VER BL5.1 CIRCULAR DRIVER | E82: DRIVER | G82: 9 | J82: =G82+H82-I82 -> 9 | K82: 150 | L82: =J82*K82 -> 1350
A83: SM0105DR13078 | B83: DR13078 | C83: 78 | D83: ADAPTOR 19V 3.5AMP | E83: ADAPTOR | G83: 50 | J83: =G83+H83-I83 -> 50 | K83: 270 | L83: =J83*K83 -> 13500
A84: SM0105DR13079 | B84: DR13079 | C84: 79 | D84: 18-24W /320MA DRIVER | E84: DRIVER | G84: 20 | J84: =G84+H84-I84 -> 20 | K84: 160 | L84: =J84*K84 -> 3200
A85: SM0105DR13080 | B85: DR13080 | C85: 80 | D85: 24-42V/120MA DRIVER | E85: DRIVER | G85: 90 | J85: =G85+H85-I85 -> 90 | K85: 160 | L85: =J85*K85 -> 14400
A86: SM0105DR13081 | B86: DR13081 | C86: 81 | D86: 5.13VER | E86: DRIVER | G86: 0 | H86: =442+100 -> 542 | I86: =100+83+259+100 -> 542 | J86: 260 | K86: 120 | L86: =J86*K86 -> 31200
C87: 82 | J87: =G87+H87-I87 -> 0 | K87: TOTAL | L87: =SUM(L6:L86) -> 986265

Sheet FG
A1: FINISHED GOODS STOCK
A3: PRODUCT CODE | B3: CATAGARE NO | C3: SLNO | D3: PART NO | E3: DESCRIPTION | F3: PHY QTY | G3: RECEIPT | H3: ISSUE | I3: BALANCE | J3: UNIT PRICE | K3: AMOUNT
A4: SM0105FG16001 | B4: FG16001 | C4: 1 | D4: 65 WATT 3.2 Amp ADAPTORE | E4: F.G | I4: =F4+G4-H4 -> 0 | J4: 100 | K4: =I4*J4 -> 0
A5: SM0105FG16002 | B5: FG16002 | C5: 2 | D5: PANAL LIGHT | E5: F.G | I5: =F5+G5-H5 -> 0 | J5: 1000 | K5: =I5*J5 -> 0
A6: SM0105FG16003 | B6: FG16003 | C6: 3 | D6: DOWN LIGHT-15LED 6WATT | E6: DOWN LIGHT | I6: =F6+G6-H6 -> 0 | J6: 1200 | K6: =I6*J6 -> 0
A7: SM0105FG16004 | B7: FG16004 | C7: 4 | D7: TUBE LIGHT - 2FEET (RETROFIT) | E7: TUBE LIGHT | G7: =1+2+10 -> 13 | H7: =1+7 -> 8 | I7: =F7+G7-H7 -> 5 | J7: 750 | K7: =I7*J7 -> 3750
A8: SM0105FG16005 | B8: FG16005 | C8: 5 | D8: TUBE LIGHT - 4FEET RETROFIT-280 LEDS | E8: TUBE LIGHT | F8: 0 | G8: =2+10+1+8+20+40 -> 81 | H8: 1 | I8: 2380 | J8: 1100 | K8: =I8*J8 -> 2618000
A9: SM0105FG16006 | B9: FG16006 | C9: 6 | D9: CDL3 WATT | E9: DOWN LIGHT | F9: 1116 | H9: =20+1+216+346 -> 583 | I9: =F9+G9-H9 -> 533 | J9: 395 | K9: =I9*J9 -> 210535
A10: SM0105FG16007 | B10: FG16007 | C10: 7 | D10: CDL5 WATT (MW) | E10: DOWN LIGHT | F10: 841 | G10: =90+36 -> 126 | H10: =1+216 -> 217 | I10: =F10+G10-H10 -> 750 | J10: 530 | K10: =I10*J10 -> 397500
A11: SM0105FG16008 | B11: FG16008 | C11: 8 | D11: CDL10 WATT ( MW) | E11: DOWN LIGHT | F11: 1240 | G11: =240+2 -> 242 | H11: =2+2+1+504 -> 509 | I11: 680 | J11: 962 | K11: =I11*J11 -> 654160
A12: SM0105FG16009 | B12: FG16009 | C12: 9 | D12: CDL15 WATT ( MW) | E12: DOWN LIGHT | F12: 1382 | G12: =160+2 -> 162 | H12: =20+18+1+552 -> 591 | I12: 560 | J12: 1180 | K12: =I12*J12 -> 660800
A13: SM0105FG16010 | B13: FG16010 | C13: 10 | D13: BULB 3WATT | E13: BULB | G13: =25+4+1 -> 30 | H13: 25 | I13: 15 | J13: 245 | K13: =I13*J13 -> 3675
A14: SM0105FG16011 | B14: FG16011 | C14: 11 | D14: BULB 5WATT | E14: BULB | G14: =25+120 -> 145 | H14: 25 | I14: =F14+G14-H14 -> 120 | J14: 330 | K14: =I14*J14 -> 39600
A15: SM0105FG16012 | B15: FG16012 | C15: 12 | D15: BULB 7WATT | E15: BULB | G15: =25+60 -> 85 | H15: 25 | I15: =F15+G15-H15 -> 60 | J15: 672 | K15: =I15*J15 -> 40320
A16: SM0105FG16013 | B16: FG16013 | C16: 13 | D16: CDLA6 WATT | E16: TUBE LIGHT | I16: =F16+G16-H16 -> 0 | J16: 600 | K16: =I16*J16 -> 0
A17: SM0105FG16014 | B17: FG16014 | C17: 14 | D17: CDLA3 WATT | E17: TUBE LIGHT | I17: =F17+G17-H17 -> 0 | J17: 400 | K17: =I17*J17 -> 0
A18: SM0105FG16015 | B18: FG16015 | C18: 15 | D18: TUBE LIGHT - 1FEET | E18: TUBE LIGHT | F18: 0 | G18: 1 | H18: 1 | I18: =F18+G18-H18 -> 0 | J18: 750 | K18: =I18*J18 -> 0
A19: SM0007FG16016 | B19: FG16016 | C19: 16 | D19: RGB LED UNDER WATER LIGHT | E19: SPOT LIGHT | I19: =F19+G19-H19 -> 0 | J19: 770 | K19: =I19*J19 -> 0
A20: SM0105FG16017 | B20: FG16017 | C20: 17 | D20: CDL- 5 Watt (WW) | E20: DOWN LIGHT | I20: 0 | J20: 550 | K20: =I20*J20 -> 0
A21: SM0105FG16018 | B21: FG16018 | C21: 18 | D21: CDL- 10 Watt (WW) | E21: DOWN LIGHT | F21: 0 | G21: 0 | H21: 0 | I21: 152 | J21: 900 | K21: =I21*J21 -> 136800
A22: SM0105FG16019 | B22: FG16019 | C22: 19 | D22: CDL- 15 Watt (WW) | E22: DOWN LIGHT | I22: 102 | J22: 1200 | K22: =I22*J22 -> 122400
A23: SM0007FG16020 | B23: FG16020 | C23: 20 | D23: Tube Light-2Ft 50 LED | E23: TUBE LIGHT | F23: 0 | G23: =1+5 -> 6 | H23: =1+5 -> 6 | I23: =F23+G23-H23 -> 0 | J23: 900 | K23: =I23*J23 -> 0
A24: SM0105FG16021 | B24: FG16021 | C24: 21 | D24: Tube Light-2Ft 50 LED(WW) | E24: TUBE LIGHT | G24: 1 | H24: 1 | I24: =F24+G24-H24 -> 0 | J24: 900 | K24: =I24*J24 -> 0
A25: SM0105FG16022 | B25: FG16022 | C25: 22 | D25: TL4FT RECTROFIT 100LED | E25: TUBE LIGHT | I25: =F25+G25-H25 -> 0 | J25: 0 | K25: =I25*J25 -> 0
A26: SM0105FG16023 | B26: FG16023 | C26: 23 | D26: TL4FT INTEGREATED 100LED (WW) | E26: TUBE LIGHT | F26: 0 | G26: =1+4+7 -> 12 | H26: =1+4+5 -> 10 | I26: 0 | J26: 1200 | K26: =I26*J26 -> 0
A27: SM0105FG16024 | B27: FG16024 | C27: 24 | D27: SPOT LIGHT- 3 Watt ME BOM | E27: SPOT LIGHT | F27: 180 | I27: =F27+G27-H27 -> 180 | J27: 450 | K27: =I27*J27 -> 81000
A28: SM0105FG16025 | B28: FG16025 | C28: 25 | D28: CDL- 6 Watt ME BOM | E28: DOWN LIGHT | I28: =F28+G28-H28 -> 0 | J28: 550 | K28: =I28*J28 -> 0
A29: SM0105FG16026 | B29: FG16026 | C29: 26 | D29: SPOT LIGHT- 6 Watt ME BOM | E29: SPOT LIGHT | F29: 238 | I29: 156 | J29: 550 | K29: =I29*J29 -> 85800
A30: SM0105FG16027 | B30: FG16027 | C30: 27 | D30: CL-10 WATT 150 LED'S | E30: CEALING LIGHT | I30: =F30+G30-H30 -> 0 | J30: 1200 | K30: =I30*J30 -> 0
A31: SM0105FG16028 | B31: FG16028 | C31: 28 | D31: 15 WATT SQUARE DOWN LIGHT | E31: DOWN LIGHT | F31: 16 | H31: =2+14 -> 16 | I31: =F31+G31-H31 -> 0 | J31: 1300 | K31: =I31*J31 -> 0
A32: SM0105FG16029 | B32: FG16029 | C32: 29 | D32: CDL- 3 Watt (WW) | E32: DOWN LIGHT | I32: 31 | J32: 395 | K32: =I32*J32 -> 12245
A33: SM0105FG16030 | B33: FG16030 | C33: 30 | D33: SPOT LIGHT 30WATT | E33: DOWN LIGHT | I33: =F33+G33-H33 -> 0 | J33: 0 | K33: =I33*J33 -> 0
A34: SM0105FG16031 | B34: FG16031 | C34: 31 | D34: DOWN LIGHT 2 X 2 | E34: DOWN LIGHT | I34: =F34+G34-H34 -> 0 | J34: 0 | K34: =I34*J34 -> 0
A35: SM0105FG16032 | B35: FG16032 | C35: 32 | D35: FLOOD LIGHT 20 WATT | E35: DOWN LIGHT | I35: =F35+G35-H35 -> 0 | J35: 0 | K35: =I35*J35 -> 0
A36: SM0105FG16033 | B36: FG16033 | C36: 33 | D36: STREET LIGHT 72 WATT | E36: DOWN LIGHT | I36: =F36+G36-H36 -> 0 | J36: 0 | K36: =I36*J36 -> 0
A37: SM0105FG16034 | B37: FG16034 | C37: 34 | D37: TL4FT RECTROFIT 100LED (MW) | E37: TUBE LIGHT | G37: =10+50+2+3+100+30+5+3 -> 203 | H37: =3+30+10+30+3+4+100+2+21 -> 203 | I37: 0 | J37: 1200 | K37: =I37*J37 -> 0
A38: SM0105FG16035 | B38: FG16035 | C38: 35 | D38: TUBELIGHT 3 FEET RETROFIT | E38: TUBE LIGHT | F38: 0 | G38: 1 | H38: 1 | I38: =F38+G38-H38 -> 0 | J38: 800 | K38: =I38*J38 -> 0
J39: TOTAL | K39: =SUM(K4:K38) -> 5066585

Sheet MOV
A3: MOV STORE STOCK
A5: RAWMATERIAL CODE | B5: CATAGARE NO | C5: SLNO | D5: PART NO | E5: DESCRIPTION | F5: PHY QTY | G5: RECEIPT | H5: ISSUE | I5: BALANCE | J5: UNIT PRICE | K5: AMOUNT
A6: VN0083MOV11001 | B6: MOV11001 | C6: 1 | D6: 440/14 | E6: MOV | F6: 30 | I6: =F6+G6-H6 -> 30 | J6: 2.3 | K6: =I6*J6 -> 69
A7: VN0083MOV11002 | B7: MOV11002 | C7: 2 | D7: 222M/400V | E7: MOV | I7: =F7+G7-H7 -> 0 | J7: 3 | K7: =I7*J7 -> 0
A8: VN0083MOV11003 | B8: MOV11003 | C8: 3 | D8: 14D471K(300/14) | E8: MOV | F8: =471+616 -> 1087 | G8: =1750+1000+1500+3500+3000 -> 10750 | H8: =10+10+400+2+702+1000+1+1600+5+15 -> 3745 | I8: =F8+G8-H8 -> 8092 | J8: 3.25 | K8: =I8*J8 -> 26299
A9: VN0083THM11004 | B9: THM11004 | C9: 4 | D9: 10D9 | E9: THERMISTER | F9: =1500+500 -> 2000 | I9: =F9+G9-H9 -> 2000 | J9: 2.85 | K9: =I9*J9 -> 5700
A10: VN0083MOV11005 | B10: MOV11005 | C10: 5 | D10: 10D471K(300/10) | E10: MOV | F10: =471 -> 471 | G10: =12000+4000+1000+4000 -> 21000 | I10: =F10+G10-H10 -> 21471 | J10: 2.9 | K10: =I10*J10 -> 62265.9
B11: MOV11006 | C11: 6 | D11: 7D471K(300/14) | E11: MOV | J11: 2.9
B12: MOV11007 | C12: 6 | D12: MOV 20D/511K | E12: MOV | F12: 22 | H12: 2 | I12: =F12+G12-H12 -> 20 | J12: 4 | K12: =I12*J12 -> 80
B13: MOV11008 | C13: 7 | D13: MOV 07D/471K | E13: MOV | F13: 63 | G13: 3000 | I13: 2000 | J13: 3 | K13: =I13*J13 -> 6000
B14: MOV11009 | C14: 8 | D14: MOV 510/14 | E14: MOV | F14: 14 | I14: =F14+G14-H14 -> 14 | J14: 4.5 | K14: =I14*J14 -> 63
B15: THM11010 | C15: 10 | D15: NTC/RES_2W | E15: THERMISTER
B16: CR18007 | C16: 9 | D16: FUSE 1AMPS FAST BLOWAXIAL TYPE 5X20 | E16: FUSE | F16: 0 | G16: 10000 | H16: 200 | I16: =F16+G16-H16 -> 9800 | J16: 2.75 | K16: =I16*J16 -> 26950
J17: TOTAL | K17: =SUM(K6:K16) -> 127426.9

Sheet WIRE
A3: WIRE STORE STOCK
A5: RAWMATERIAL CODE | B5: CATAGARE NO | C5: SLNO | D5: PART NO | E5: DESCRIPTION | F5: PHY QTY | G5: RECEIPT | H5: ISSUE | I5: BALANCE | J5: UNIT PRICE | K5: AMOUNT
A6: VN0018WR12001 | B6: WR12001 | C6: 1 | D6: 14 Stands Black Wire (Bundle) | E6: Wire | F6: 13 | G6: 12 | H6: =1+2 -> 3 | I6: =F6+G6-H6 -> 22 | J6: 190 | K6: =I6*J6 -> 4180
A7: VN0018WR12002 | B7: WR12002 | C7: 2 | D7: 14 Stands Red Wire (Bundle) | E7: Wire | F7: 30 | G7: 13 | I7: =F7+G7-H7 -> 43 | J7: 190 | K7: =I7*J7 -> 8170
B8: WR12003 | C8: 3 | D8: 19 StrandsTEFLON WIRE | E8: WIRE | F8: 0 | G8: =10+10 -> 20 | H8: =1+2+4+1+1+1+2 -> 12 | I8: =F8+G8-H8 -> 8 | J8: 975 | K8: =I8*J8 -> 7800
B9: WR12004 | C9: 4 | D9: 19 stands tefflon wire Red | E9: Wire
B10: WR12005 | C10: 5 | D10: 19 stands tefflon wire Black | E10: Wire
J12: TOTAL | K12: =SUM(K6:K11) -> 20150

Sheet ASSACERIES
A3: ASSAACERIES STORE STOCK
A5: RAWMATERIAL CODE | B5: CATAGARE NO | C5: SLNO | D5: PART NO | E5: DESCRIPTION | F5: PHY QTY | G5: RECEIPT | H5: ISSUE | I5: BALANCE | J5: UNIT PRICE | K5: AMOUNT
A6: VN0051EQ10001 | B6: EQ10001 | C6: 1 | D6: GE 2000 | E6: SILENT | F6: 0 | I6: =F6+G6-H6 -> 0 | J6: 150 | K6: =I6*J6 -> 0
A7: VN0009EQ10002 | B7: EQ10002 | C7: 2 | D7: V20-C/1+NPE,320V | E7: SWITCH | F7: 0 | I7: =F7+G7-H7 -> 0 | J7: 5 | K7: =I7*J7 -> 0
A8: VN0009EQ10003 | B8: EQ10003 | C8: 3 | D8: TNR-C20 | E8: SWITCH | I8: =F8+G8-H8 -> 0 | J8: 5 | K8: =I8*J8 -> 0
A9: VN0051EQ10002 | B9: EQ10004 | C9: 4 | D9: Cello Tape | E9: TAPE | I9: =F9+G9-H9 -> 0 | J9: 38 | K9: =I9*J9 -> 0
A10: VN0009EQ10004 | B10: EQ10005 | C10: 5 | D10: Packing Tape | E10: 2" 50mm Length, Brown Tape | I10: 5 | J10: 38 | K10: =I10*J10 -> 190
A11: VN0093EQ10006 | B11: EQ10006 | C11: 6 | D11: M3 x 6.5 mm Self Tap Screw | E11: Screw | I11: =F11+G11-H11 -> 0 | J11: 2 | K11: =I11*J11 -> 0
A12: VN0045EQ10007 | B12: EQ10007 | C12: 7 | D12: F.G.SLEEVING Nonshinkable Sleeve (4MM-WHITE) | E12: Nonshinkable Sleeve | I12: =F12+G12-H12 -> 0 | J12: 200 | K12: =I12*J12 -> 0
A13: VN0112EQ10008 | B13: EQ10008 | C13: 8 | D13: FIBRE GLASS SLEEVE 3 mm Sleeve | E13: Shinkable Sleeve | G13: 100 | H13: 100 | I13: =F13+G13-H13 -> 0 | J13: 1.65 | K13: =I13*J13 -> 0
A14: VN0023EQ10009 | B14: EQ10009 | C14: 9 | D14: Anabond | E14: Thermal Adhesive | G14: 5 | I14: =F14+G14-H14 -> 5 | J14: 80 | K14: =I14*J14 -> 400 | L14: SAW INVOICE
A15: VN0073EQ10010 | B15: EQ10010 | C15: 10 | D15: Solder lead | E15: Tin Lead | I15: =F15+G15-H15 -> 0 | J15: 675 | K15: =I15*J15 -> 0
A16: VN0073EQ10011 | B16: EQ10011 | C16: 11 | D16: Solder flux | E16: Ammonium Chlride or Rosin | I16: =F16+G16-H16 -> 0 | J16: 500 | K16: =I16*J16 -> 0
A17: VN0073EQ10012 | B17: EQ10012 | C17: 12 | D17: I P A | E17: ISO PROPYLE ALCHOCOL | F17: 0 | G17: 5 | I17: =F17+G17-H17 -> 5 | J17: 95 | K17: =I17*J17 -> 475
A18: VN0002EQ10013 | B18: EQ10013 | C18: 13 | D18: Cotton waste | E18: White Cotton waste | I18: 2 | J18: 100 | K18: =I18*J18 -> 200
A19: VN0113EQ10014 | B19: EQ10014 | C19: 14 | D19: Packing Box | E19: 195x195x195mm | I19: =F19+G19-H19 -> 0 | K19: =I19*J19 -> 0
A20: VN0041EQ10015 | B20: EQ10015 | C20: 15 | D20: 384 Locktite | E20: Locktite | I20: =F20+G20-H20 -> 0 | J20: 1150 | K20: =I20*J20 -> 0
A21: VN0045EQ10016 | B21: EQ10016 | C21: 16 | D21: Polythine Sheet | E21: Polyester Film (5Mil-milky) | I21: =F21+G21-H21 -> 0 | J21: 300 | K21: =I21*J21 -> 0
A22: VN0023EQ10017 | B22: EQ10017 | C22: 17 | D22: 203 Fewiquick | E22: Fewiquick | F22: 0 | I22: =F22+G22-H22 -> 0 | J22: 55 | K22: =I22*J22 -> 0
A23: VN0023EQ10018 | B23: EQ10018 | C23: 18 | D23: BROWN TAPE 2" | E23: TAPE | I23: =F23+G23-H23 -> 0 | J23: 38 | K23: =I23*J23 -> 0
A24: VN0113EQ10019 | B24: EQ10019 | C24: 19 | D24: CIRCUIT LACQUER 400ML (6130005500) AMBERSIL | E24: CIRCUIT LACQUER | I24: =F24+G24-H24 -> 0 | J24: 450 | K24: =I24*J24 -> 0
A25: VN0113EQ10020 | B25: EQ10020 | C25: 20 | D25: TUBE LIGHT -4 FT COTTON BOX (126 X 430 X 430 ) | E25: Packing Box | I25: =F25+G25-H25 -> 0 | J25: 101 | K25: =I25*J25 -> 0
A26: VN0113EQ10021 | B26: EQ10021 | C26: 21 | D26: TUBE LIGHT -2 FT COTTON BOX (126 X 430 X 430 ) | E26: Packing Box | I26: =F26+G26-H26 -> 0 | J26: 69 | K26: =I26*J26 -> 0
A27: VN0113EQ10022 | B27: EQ10022 | C27: 22 | D27: T8-TUBE LIGHT -DRIVER COTTON BOX | E27: Packing Box | I27: =F27+G27-H27 -> 0 | J27: 21 | K27: =I27*J27 -> 0
A28: VN0113EQ10023 | B28: EQ10023 | C28: 24 | D28: 15 WATT DOWN LIGHT COTTON BOX | E28: Packing Box | I28: =F28+G28-H28 -> 0 | J28: 9 | K28: =I28*J28 -> 0
A29: VN0113EQ10024 | B29: EQ10024 | C29: 25 | D29: TUBE LIGHT BOX (L-40 X 1240X40 ) | E29: Packing Box | I29: =F29+G29-H29 -> 0 | J29: 6 | K29: =I29*J29 -> 0
A30: VN0045EQ10025 | B30: EQ10025 | C30: 26 | D30: TUBE LIGHT HEAT SINKABLE SLEEVE 10 MM | E30: Shinkable Sleeve | I30: =F30+G30-H30 -> 0 | J30: 9 | K30: =I30*J30 -> 0
B31: EQ10026 | C31: 27 | D31: BUBBLE COVER | E31: BUBBLE ROLLE | I31: =F31+G31-H31 -> 0 | J31: 1300 | K31: =I31*J31 -> 0
B32: EQ10027 | C32: 28 | D32: GLU STICK | E32: GLU STICK | F32: 0 | G32: 30 | H32: =5+5+3+3 -> 16 | I32: 35 | J32: 9 | K32: =I32*J32 -> 315
B33: EQ10028 | C33: 29 | D33: BALE PATTI | E33: BALE PATTI | I33: =F33+G33-H33 -> 0 | K33: =I33*J33 -> 0
B34: EQ10029 | C34: 30 | D34: OK STICKER | E34: STICKER | I34: =F34+G34-H34 -> 0 | K34: =I34*J34 -> 0
B35: EQ10030 | C35: 31 | D35: PVC INSULATION TAPE | E35: INSULATION TAPE | I35: =F35+G35-H35 -> 0 | J35: 10 | K35: =I35*J35 -> 0
B36: EQ10031 | C36: 31 | D36: Cello Tape 1" | E36: TAPE | K36: 0
B37: EQ10032 | C37: 32 | D37: HEAT SHRINKABE SLEEVE 16MM | E37: SLEEVE | F37: 100 | H37: 100 | I37: =F37+G37-H37 -> 0 | K37: =I37*J37 -> 0
B38: EQ10033 | C38: 38 | D38: HEAT SHRINKABE SLEEVE 18MM | E38: SHRINKABBLE SLEEVE | F38: 0 | G38: =100+100 -> 200 | H38: 200 | I38: =F38+G38-H38 -> 0 | J38: 16 | K38: =I38*J38 -> 0
B39: EQ10034 | C39: 34 | D39: BULB CAP | E39: BULB CAP | F39: 7 | I39: =F39+G39-H39 -> 7 | K39: =I39*J39 -> 0
B40: EQ10035 | C40: 35 | D40: TUBE LIGHT CLAMPS | E40: CLAMPS | F40: 230 | I40: =F40+G40-H40 -> 230 | K40: =I40*J40 -> 0
B41: EQ10036 | C41: 36 | D41: TUBE LIGHT DIFFUSER -PC SERAATION TYPE | E41: DIFFUSER | F41: 5 | G41: 50 | I41: =F41+G41-H41 -> 55 | J41: 35 | K41: =I41*J41 -> 1925
B42: EQ10037 | C42: 37 | D42: TUBE LIGHT DIFFUSER -PC CLEAR TYPE | E42: DIFFUSER | F42: 7 | G42: 0 | H42: 1 | I42: =F42+G42-H42 -> 6 | J42: 35 | K42: =I42*J42 -> 210
B43: EQ10038 | C43: 33 | D43: INTEGRATED END CAP TUBE LIGHT | E43: END CAP | F43: 49 | H43: =4+30+2+10+3 -> 49 | I43: =F43+G43-H43 -> 0 | K43: =I43*J43 -> 0
B44: EQ10039 | C44: 39 | D44: BATTERY | E44: TIMER LITHIUM CELL | I44: =F44+G44-H44 -> 0 | K44: =I44*J44 -> 0
B45: EQ10040 | C45: 40 | D45: BATTERY HOLDER | E45: TIMER LITHIUM CELL HOLDER | I45: =F45+G45-H45 -> 0 | K45: =I45*J45 -> 0
B46: EQ10041 | C46: 41 | D46: 11.0592MHZ | E46: TIMER CRISTAL OSSILATOR | I46: =F46+G46-H46 -> 0 | K46: =I46*J46 -> 0
B47: EQ10042 | C47: 42 | D47: PIC16F886 | E47: TIMER MICROCONTROLLER | I47: =F47+G47-H47 -> 0 | K47: =I47*J47 -> 0
B48: EQ10043 | C48: 43 | D48: 11.0592MHZ | E48: CRISTAL OSSILATOR | I48: =F48+G48-H48 -> 0 | K48: =I48*J48 -> 0
B49: EQ10044 | C49: 44 | D49: 32KHZ | E49: CRISTAL OSSILATOR | I49: =F49+G49-H49 -> 0 | K49: =I49*J49 -> 0
B50: EQ10045 | C50: 39 | D50: SS SCRES M3X6 CHEESE HEAD | E50: Screw | F50: 0 | G50: 5000 | I50: =F50+G50-H50 -> 5000 | J50: 0.8 | K50: =I50*J50 -> 4000
B51: EQ10046 | C51: 46 | D51: M3 X 13 SCREW | E51: SCREW | I51: =F51+G51-H51 -> 0 | K51: =I51*J51 -> 0
B52: EQ10047 | C52: 47 | D52: M3 PLASTIC WASHER | E52: WASHER | I52: =F52+G52-H52 -> 0 | K52: =I52*J52 -> 0
B53: EQ10048 | C53: 48 | D53: FASCOAT 20 X 10 4UPS 1 INCH | E53: BAR CODING LABEL | I53: =F53+G53-H53 -> 0 | K53: =I53*J53 -> 0
B54: EQ10049 | C54: 49 | D54: MSRW 25 WATTS;120E | E54: MEGA WIREWOUND RESISTORS | I54: =F54+G54-H54 -> 0 | K54: =I54*J54 -> 0
B55: EQ10050 | C55: 50 | D55: MSRW 25 WATTS;166E | E55: MEGA WIREWOUND RESISTORS | I55: =F55+G55-H55 -> 0 | K55: =I55*J55 -> 0
B56: EQ10051 | C56: 51 | D56: MASTER COTTON BOX (350X340X245) | E56: Packing Box | F56: 250 | G56: 36 | I56: =F56+G56-H56 -> 286 | K56: =I56*J56 -> 0
B57: EQ10052 | C57: 52 | D57: MSRW 20 WATTS;400E | E57: MEGA WIREWOUND RESISTORS | I57: =F57+G57-H57 -> 0 | K57: =I57*J57 -> 0
B58: EQ10053 | C58: 53 | D58: PACKING CRATE FOR CHANNAL TRAY | E58: TUBE LIGHT DRIVER PACKING TRAY | F58: 16 | I58: =F58+G58-H58 -> 16 | K58: =I58*J58 -> 0
B59: EQ10054 | C59: 54 | D59: 10-15 WATT COTTON BOX(610 X 415 ) | E59: MASTER COTTON BOX FOR 10 AND 15 WATT | I59: =F59+G59-H59 -> 0 | K59: =I59*J59 -> 0
B60: EQ10055 | C60: 55 | D60: 5 WATT COTTON BOX(395 X 265 ) | E60: MASTER COTTON BOX FOR 5 WATT | I60: =F60+G60-H60 -> 0 | K60: =I60*J60 -> 0
B61: EQ10056 | C61: 56 | D61: 3 WATT COTTON BOX | E61: MASTER COTTON BOX FOR 3 WATT | I61: =F61+G61-H61 -> 0 | K61: =I61*J61 -> 0
B62: EQ10057 | C62: 57 | D62: MSRW 30 WATTS;390E | E62: MEGA WIREWOUND RESISTORS | I62: =F62+G62-H62 -> 0 | K62: =I62*J62 -> 0
B63: EQ10058 | C63: 58 | D63: MSRW 20 WATTS;94E | E63: MEGA WIREWOUND RESISTORS | I63: =F63+G63-H63 -> 0 | K63: =I63*J63 -> 0
B64: EQ10059 | C64: 59 | D64: MSRW 20 WATTS;142E | E64: MEGA WIREWOUND RESISTORS | I64: =F64+G64-H64 -> 0 | K64: =I64*J64 -> 0
B65: EQ10060 | C65: 60 | D65: MSRW 20 WATTS;185E | E65: MEGA WIREWOUND RESISTORS | I65: =F65+G65-H65 -> 0 | K65: =I65*J65 -> 0
B66: EQ10061 | C66: 61 | D66: MSRW 20 WATTS;67E | E66: MEGA WIREWOUND RESISTORS | I66: =F66+G66-H66 -> 0 | K66: =I66*J66 -> 0
B67: EQ10062 | C67: 62 | D67: MSRW 20 WATTS;80E | E67: MEGA WIREWOUND RESISTORS | I67: =F67+G67-H67 -> 0 | K67: =I67*J67 -> 0
B68: EQ10063 | C68: 63 | D68: MSRW 20 WATTS;62E | E68: MEGA WIREWOUND RESISTORS | I68: =F68+G68-H68 -> 0 | K68: =I68*J68 -> 0
B69: EQ10064 | C69: 64 | D69: MSRW 20 WATTS;114E | E69: MEGA WIREWOUND RESISTORS | I69: =F69+G69-H69 -> 0 | K69: =I69*J69 -> 0
B70: EQ10065 | C70: 65 | D70: MSRW 10 WATTS;27E | E70: MEGA WIREWOUND RESISTORS | I70: =F70+G70-H70 -> 0 | K70: =I70*J70 -> 0
B71: EQ10066 | C71: 66 | D71: MSRW 120 WATTS;400E | E71: MEGA WIREWOUND RESISTORS | I71: =F71+G71-H71 -> 0 | K71: =I71*J71 -> 0
B72: EQ10067 | C72: 67 | D72: CORRUGATED BOARD AND BOXES 3 PLY BOXES WITH PUNCHING | E72: MARUTHI PUNCH PACK | F72: 300 | G72: 18 | I72: =F72+G72-H72 -> 318 | K72: =I72*J72 -> 0
B73: EQ10068 | C73: 68 | D73: 5 PLY MASTER COTTON BOX | E73: MARUTHI PUNCH PACK | F73: 19 | I73: =F73+G73-H73 -> 19 | K73: =I73*J73 -> 0
B74: EQ10069 | C74: 69 | D74: BAR CODE STICKER | I74: =F74+G74-H74 -> 0 | K74: =I74*J74 -> 0
B75: EQ10070 | C75: 70 | D75: LABLE STICKER | I75: =F75+G75-H75 -> 0 | K75: =I75*J75 -> 0
B76: EQ10072 | C76: 72 | D76: MSRW 10 WATTS;47E | E76: SHREE ELECTRONICS | F76: 200 | G76: 3 | I76: =F76+G76-H76 -> 203 | K76: =I76*J76 -> 0
B77: EQ10073 | C77: 73 | D77: BALE PATTI CLIPS | E77: SEAPAC SYSTEMS | F77: 1 | G77: 70 | I77: =F77+G77-H77 -> 71 | K77: =I77*J77 -> 0
B78: EQ10074 | C78: 74 | D78: BROWN TAPE 3" | E78: SEAPAC SYSTEMS | F78: 48 | G78: 43 | I78: =F78+G78-H78 -> 91 | K78: =I78*J78 -> 0
B79: EQ10075 | C79: 75 | D79: STRETCH WRAP FILM ROLL 500MM X 23 MICRON | E79: STRETCH WRAP | F79: 5.1 | G79: 156.13 | I79: =F79+G79-H79 -> 161.23 | K79: =I79*J79 -> 0
J80: Total | K80: =SUM(K6:K79) -> 7715

Sheet IC
A2: IC STORE STOCK
A4: RAWMATERIAL CODE | B4: CATAGARE NO | C4: SLNO | D4: PART NO | E4: DESCRIPTION | F4: PHY QTY | G4: RECEIPT | H4: ISSUE | I4: BALANCE | J4: UNIT PRICE | K4: AMOUNT
A5: SM0105IC15001 | B5: IC15001 | C5: 1 | D5: SM3300 | E5: IC | F5: =8220+200 -> 8420 | G5: 32000 | H5: =10+2+500+1000+250+702+100+50+1000+50+5+1+10 -> 3680 | I5: =F5+G5-H5 -> 36740 | J5: 15 | K5: =I5*J5 -> 551100 | L5: =+K5/$K$26 -> 0.7522158
A6: SM0105IC15002 | B6: IC15002 | C6: 2 | D6: SM8900 | E6: IC | F6: 1376 | I6: =F6+G6-H6 -> 1376 | J6: 15 | K6: =I6*J6 -> 20640 | L6: =+K6/$K$26 -> 0.028172263
A7: SM0105IC15003 | B7: IC15003 | C7: 3 | D7: CS8902 | E7: IC | F7: =1549+2500 -> 4049 | I7: =F7+G7-H7 -> 4049 | J7: 15 | K7: =I7*J7 -> 60735 | L7: =+K7/$K$26 -> 0.082899341
A8: VN0035IC15004 | B8: IC15004 | C8: 4 | D8: FAN7346MX SCR SGP | E8: IC | F8: 10 | I8: =F8+G8-H8 -> 10 | J8: 20 | K8: =I8*J8 -> 200 | L8: =+K8/$K$26 -> 0.00027298704
A9: VN0035IC15005 | B9: IC15005 | C9: 5 | D9: 23AB FO8H60S | E9: IC | F9: 19 | I9: =F9+G9-H9 -> 19 | J9: 15 | K9: =I9*J9 -> 285 | L9: =+K9/$K$26 -> 0.00038900654
A10: VN0035IC15006 | B10: IC15006 | C10: 6 | D10: FL7930BMX SCR SGP | E10: IC | F10: 10 | I10: =F10+G10-H10 -> 10 | J10: 10 | K10: =I10*J10 -> 100 | L10: =+K10/$K$26 -> 0.00013649352
A11: VN0035IC15007 | B11: IC15007 | C11: 7 | D11: B19AC FLS 1800XS | E11: IC | I11: =F11+G11-H11 -> 0 | J11: 15 | K11: =I11*J11 -> 0 | L11: =+K11/$K$26 -> 0
A12: VN0035IC15008 | B12: IC15008 | C12: 8 | D12: 1B46AC-FDPF12N60 NZ | E12: IC | I12: =F12+G12-H12 -> 0 | J12: 10 | K12: =I12*J12 -> 0 | L12: =+K12/$K$26 -> 0
A13: VN0035IC15009 | B13: IC15009 | C13: 9 | D13: 12F675 | E13: IC | I13: =F13+G13-H13 -> 0 | J13: 12 | K13: =I13*J13 -> 0 | L13: =+K13/$K$26 -> 0
A14: VN0035IC15010 | B14: IC15010 | C14: 10 | D14: SM6300A | E14: IC | F14: 99 | I14: =F14+G14-H14 -> 99 | J14: 20 | K14: =I14*J14 -> 1980 | L14: =+K14/$K$26 -> 0.0027025717
A15: VN0035IC15011 | B15: IC15011 | C15: 11 | D15: SMD ICSSW2802 SOT23-6 | E15: IC | F15: 500 | I15: =F15+G15-H15 -> 500 | J15: 20 | K15: =I15*J15 -> 10000 | L15: =+K15/$K$26 -> 0.013649352
A16: VN0035IC15012 | B16: IC15012 | C16: 12 | D16: SKW1126 | E16: IC | I16: =F16+G16-H16 -> 0 | J16: 20 | K16: =I16*J16 -> 0 | L16: =+K16/$K$26 -> 0
A17: VN0035IC15013 | B17: IC15013 | C17: 13 | D17: SSW2601A | E17: IC | I17: =F17+G17-H17 -> 0 | J17: 20 | K17: =I17*J17 -> 0 | L17: =+K17/$K$26 -> 0
A18: VN0035IC15014 | B18: IC15014 | C18: 14 | D18: Printing Mark | E18: IC | I18: =F18+G18-H18 -> 0 | J18: 20 | K18: =I18*J18 -> 0 | L18: =+K18/$K$26 -> 0
A19: SM0105IC15015 | B19: IC15015 | C19: 15 | D19: SM6300B | E19: IC | F19: =3000+3000+317+130 -> 6447 | H19: =10+400+20+5+1+8+2000+1+1000 -> 3445 | I19: =F19+G19-H19 -> 3002 | J19: 20 | K19: =I19*J19 -> 60040 | L19: =+K19/$K$26 -> 0.081950711
B20: IC15016 | C20: 16 | D20: SM2601A | E20: IC | F20: 970 | H20: =50+100+6 -> 156 | I20: =F20+G20-H20 -> 814 | J20: 18 | K20: =I20*J20 -> 14652 | L20: =+K20/$K$26 -> 0.019999031
B21: IC15017 | C21: 17 | D21: SMA6301 | E21: IC | F21: 600 | I21: =F21+G21-H21 -> 600 | J21: 20 | K21: =I21*J21 -> 12000 | L21: =+K21/$K$26 -> 0.016379223
B22: IC15018 | C22: 18 | D22: IE817 | E22: IC | F22: =70+75+40 -> 185 | I22: =F22+G22-H22 -> 185 | J22: 2.5 | K22: =I22*J22 -> 462.5 | L22: =+K22/$K$26 -> 0.00063128254
B23: IC15019 | C23: 19 | D23: IC BASE 28 PIN 2.54MM | E23: IC BASE | F23: 63 | I23: =F23+G23-H23 -> 63 | J23: 7 | K23: =I23*J23 -> 441 | L23: =+K23/$K$26 -> 0.00060193643
B24: IC15020 | C24: 20 | D24: SM UA 2121 JC | E24: IC | F24: 100 | I24: =F24+G24-H24 -> 100 | J24: 8 | K24: =I24*J24 -> 800 | L24: =+K24/$K$26 -> 0.0010919482
B25: IC15021 | C25: 21 | D25: AT 7373 | E25: IC | F25: 20 | I25: =F25+G25-H25 -> 20 | J25: 9 | K25: =I25*J25 -> 180 | L25: =+K25/$K$26 -> 0.00024568834
J26: TOTAL | K26: =SUM(K5:K23) -> 732635.5

Sheet ENCLOSURES
A1: ENCLOSURE STORE STOCK
A3: RAWMATERIAL CODE | B3: CATAGARE NO | C3: SLNO | D3: PART NO | E3: DESCRIPTION | F3: PHY QTY | G3: UNIT PRICE | H3: AMOUNT
A4: VN0004ES07001 | B4: ES07001 | C4: 1 | D4: Down Light 3 Watt Enclosure | E4: ENCLOSURE | F4: 0 | G4: 37.4 | H4: =G4*F4 -> 0
A5: VN0004ES07002 | B5: ES07002 | C5: 2 | D5: Down Light 5 Watt Enclosure | E5: ENCLOSURE | F5: 0 | G5: 49.5 | H5: =G5*F5 -> 0
A6: VN0004ES07003 | B6: ES07003 | C6: 3 | D6: Down Light 9 Watt Enclosure | E6: ENCLOSURE | F6: 0 | G6: 55 | H6: =G6*F6 -> 0
A7: VN0004ES07004 | B7: ES07004 | C7: 4 | D7: Down Light 15 Watt Enclosure | E7: ENCLOSURE | F7: 0 | G7: 60.5 | H7: =G7*F7 -> 0
A8: VN0007ES07005 | B8: ES07005 | C8: 5 | D8: T8-TUBE LIGHT FIXTURE | E8: ENCLOSURE | F8: 0 | G8: 120 | H8: =G8*F8 -> 0
A9: VN0004ES07006 | B9: ES07006 | C9: 6 | D9: 1 X 1 DLS | E9: ENCLOSURE | F9: 2 | G9: 420 | H9: =G9*F9 -> 840
A10: VN0004ES07007 | B10: ES07007 | C10: 7 | D10: MAK DLP 1080 5W DOWN LIGHT ECO PLUS FITTINGS | E10: ENCLOSURE | F10: 0 | G10: 175 | H10: =G10*F10 -> 0
A11: VN0004ES07008 | B11: ES07008 | C11: 8 | D11: 1/2 FEET DLS | E11: ENCLOSURE | F11: 1 | G11: 150 | H11: =G11*F11 -> 150
A12: VN0004ES07009 | B12: ES07009 | C12: 9 | D12: T8 TUBE LIGHT LOADS | E12: ENCLOSURE | F12: 0 | G12: 750 | H12: =G12*F12 -> 0
A13: VN0004ES07010 | B13: ES07010 | C13: 10 | D13: BULP WHITE ENCLOSURE 3WATT | E13: ENCLOSURE | F13: 20 | G13: 77 | H13: =G13*F13 -> 1540
A14: VN0004ES07011 | B14: ES07011 | C14: 11 | D14: BULP WHITE ENCLOSURE 7WATT | E14: ENCLOSURE | F14: 92 | G14: 95 | H14: =G14*F14 -> 8740
A15: VN0004ES07012 | B15: ES07012 | C15: 12 | D15: BULP SILVER ENCLOSURE 10WATT | E15: ENCLOSURE | F15: 10 | G15: 105 | H15: =G15*F15 -> 1050
... A29: VN0007ES07026 | B29: ES07026 | C29: 26 | D29: LED CEILING LIGHT HOUSING+SMD3528 9W,PCBA | E29: ENCLOSURE | F29: 0 | G29: 181.5 | H29: =G29*F29 -> 0
B30: ES07027 | C30: 27 | D30: channel T8 4 Feet Regular | E30: ENCLOSURE | F30: 20 | G30: 40 | H30: =G30*F30 -> 800
B31: ES07028 | C31: 28 | D31: RGB LED UNDER WATER LIGHT | E31: ENCLOSURE | F31: 0 | G31: 0 | H31: =G31*F31 -> 0
B32: ES07029 | C32: 29 | D32: LED CEILING LIGHT HOUSING+SMD5730 (MW) | E32: ENCLOSURE | F32: 0 | G32: 236.5 | H32: =G32*F32 -> 0
B33: ES07030 | C33: 30 | D33: T8 TUBE LIGHT PATTI 12 X 40 | E33: ENCLOSURE | F33: 0 | G33: 0 | H33: =G33*F33 -> 0
B34: ES07031 | C34: 31 | D34: HB-04 | E34: ENCLOSURE | F34: 0 | G34: 0 | H34: =G34*F34 -> 0
B35: ES07032 | C35: 32 | D35: T5 LED FITTING 2FT (INTEGREATED ) | E35: ENCLOSURE | F35: 0 | G35: 130 | H35: =G35*F35 -> 0
B36: ES07033 | C36: 33 | D36: Down Light 3 Watt Enclosure (Alluminium) | E36: ENCLOSURE | F36: 0 | G36: 0 | H36: =G36*F36 -> 0
B37: ES07034 | C37: 34 | D37: Down Light 6 Watt Enclosure (Alluminium) | E37: ENCLOSURE | F37: 0 | G37: 0 | H37: =G37*F37 -> 0
B38: ES07035 | C38: 35 | D38: LED DRIVER-04 | E38: ENCLOSURE | F38: 0 | G38: 7 | H38: =G38*F38 -> 0
B39: ES07036 | C39: 36 | D39: T8 TUBE LIGHT PATTI 2 FEET | E39: ENCLOSURE | F39: 0 | G39: 0 | H39: =G39*F39 -> 0
B40: ES07037 | C40: 37 | D40: T8-TUBE LIGHT RECTROFIT 4FT | E40: ENCLOSURE | F40: 1180 | G40: 180 | H40: =G40*F40 -> 212400
B41: ES07038 | C41: 38 | D41: 15 WATT SQUARE DOWN LIGHT ENCLOSURE | E41: ENCLOSURE | F41: 0 | G41: 0 | H41: =G41*F41 -> 0
... B48: ES07045 | C48: 45 | D48: END CAP PIN | E48: ENCLOSURE | F48: 0 | G48: 0 | H48: =G48*F48 -> 0
G49: TOTAL | H49: =SUM(H4:H42) -> 582903.5

Sheet TOTAL PRICE
B3: TOTAL AMOUNT
B5: SL NO | C5: DESCRIPTION | D5: AMOUNT
B6: 1 | C6: PCB | D6: =PCB!K94 -> 3147598.8 | E6: =+D6/$D$22 -> #REF!
B7: 2 | C7: DIODE | D7: =DIODE!K27 -> 157386.9 | E7: =+D7/$D$22 -> #REF!
B8: 3 | C8: RESISTORS | D8: =RESISTOR!N203 -> 117692.79 | E8: =+D8/$D$22 -> #REF!
B9: 4 | C9: CONNECTOR | D9: =CONNECTOR!K15 -> 57250 | E9: =+D9/$D$22 -> #REF!
B10: 5 | C10: LEDS | D10: =LEDS!K30 -> 997867.7 | E10: =+D10/$D$22 -> #REF!
B11: 6 | C11: CAPACITOR | D11: =CAPACITOR!K101 -> 373427.95 | E11: =+D11/$D$22 -> #REF!
B12: 7 | C12: HEATSINK | D12: =HEATSINK!K11 -> 210 | E12: =+D12/$D$22 -> #REF!
B13: 8 | C13: INDUCTOR | D13: =INDUCTOR!K36 -> 103494.59 | E13: =+D13/$D$22 -> #REF!
B14: 9 | C14: MOSFET | D14: =MOSFET!K17 -> 896288.5 | E14: =+D14/$D$22 -> #REF!
B15: 10 | C15: DRIVER | D15: =DRIVER!L87 -> 986265 | E15: =+D15/$D$22 -> #REF!
B16: 11 | C16: FG | D16: =FG!K39 -> 5066585 | E16: =+D16/$D$22 -> #REF!
B17: 12 | C17: MOV | D17: =MOV!K17 -> 127426.9 | E17: =+D17/$D$22 -> #REF!
B18: 13 | C18: WIRE | D18: =WIRE!K12 -> 20150 | E18: =+D18/$D$22 -> #REF!
B19: 14 | C19: ASSECERIES | D19: =ASSACERIES!#REF! -> #REF! | E19: =+D19/$D$22 -> #REF!
B20: 15 | C20: IC | D20: =IC!K26 -> 732635.5 | E20: =+D20/$D$22 -> #REF!
B21: 16 | C21: ENCLOSURES | D21: =ENCLOSURES!H49 -> 582903.5 | E21: =+D21/$D$22 -> #REF!
C22: TOTAL | D22: =SUM(D6:D21) -> #REF!

Sheet VENDER NAME&CODE
B3: SL NO | C3: VENDER CODE | D3: VENDER NAME
B4: 1 | C4: VN0001 | D4: A R ENTERPRISES
B5: 2 | C5: VN0002 | D5: Asiatic Stationers
B6: 3 | C6: VN0003 | D6: Aarthi Electronics
B7: 4 | C7: VN0004 | D7: ALTIS LIGHTING SOLUTIONS(MAKLITES GROUP)
B8: 5 | C8: VN0005 | D8: ADVANCE MICRO COMPONENTS
B9: 6 | C9: VN0006 | D9: AKHILA BHARATH ENTERPRISES
B10: 7 | C10: VN0007 | D10: ANLITE
B11: 8 | C11: VN0008 | D11: Ananya Products,Mathikere,Mb 93411 31703
B12: 9 | C12: VN0009 | D12: ANKIT
B13: 10 | C13: VN0010 | D13: ATS TECHNOLOGIES
B14: 11 | C14: VN0011 | D14: B T Technologies
B15: 12 | C15: VN0012 | D15: BALAJI GLASS HOUSE
... B120: 118 | C120: VN0117 | D120: MARUTHI PUNCH PACK

Sheet Sheet1

Sheet Sheet2
